Workbook

Sheet 总览
A1: 7天海外版上线推进看板
A3: 原7天运营计划保留；新增“研发总览、开发进度、测试进度、模拟对局、部署方案”。开发/测试/部署请以新增工作表为主。
A5: 项目开始日期（可修改） | C5: 46215 | E5: 目标上线日期 | G5: =C5+6 -> 46221 | I5: 当前第几天 | K5: =MAX(1,MIN(7,TODAY()-C5+1)) -> 5 | M5: 使用方式：在“7天任务”中更新状态
A7: =COUNTA('7天任务'!E5:E200) -> 72 | C7: =COUNTIF('7天任务'!H5:H200,"已完成") -> 18 | E7: =COUNTIF('7天任务'!H5:H200,"进行中")+COUNTIF('7天任务'!H5:H200,"待审核") -> 5 | G7: =COUNTIF('7天任务'!H5:H200,"已阻塞") -> 0 | I7: =IFERROR(AVERAGE('7天任务'!I5:I200),0) -> 0.28472222
A10: 总任务 | C10: 已完成 | E10: 进行中 / 待审核 | G10: 已阻塞 | I10: 总体完成率
A12: 按分类查看进度 | H12: 按天查看进度
A13: 分类 | B13: 任务数 | C13: 已完成 | D13: 进行中/待审核 | E13: 已阻塞 | F13: 完成率 | H13: 天数 | I13: 日期 | J13: 任务数 | K13: 已完成 | L13: 已阻塞 | M13: 完成率
A14: 产品开发与上线 | B14: =COUNTIF('7天任务'!$D$5:$D$200,A14) -> 17 | C14: =COUNTIFS('7天任务'!$D$5:$D$200,A14,'7天任务'!$H$5:$H$200,"已完成") -> 2 | D14: =COUNTIFS('7天任务'!$D$5:$D$200,A14,'7天任务'!$H$5:$H$200,"进行中")+COUNTIFS('7天任务'!$D$5:$D$200,A14,'7天任务'!$H$5:$H$200,"待审核") -> 2 | E14: =COUNTIFS('7天任务'!$D$5:$D$200,A14,'7天任务'!$H$5:$H$200,"已阻塞") -> 0 | F14: =IFERROR(SUMIF('7天任务'!$D$5:$D$200,A14,'7天任务'!$I$5:$I$200)/COUNTIF('7天任务'!$D$5:$D$200,A14),0) -> 0.17647059 | H14: 第1天 | I14: =$C$5+0 -> 46215 | J14: =COUNTIF('7天任务'!$B$5:$B$200,1) -> 18 | K14: =COUNTIFS('7天任务'!$B$5:$B$200,1,'7天任务'!$H$5:$H$200,"已完成") -> 12 | L14: =COUNTIFS('7天任务'!$B$5:$B$200,1,'7天任务'!$H$5:$H$200,"已阻塞") -> 0 | M14: =IFERROR(SUMIF('7天任务'!$B$5:$B$200,1,'7天任务'!$I$5:$I$200)/COUNTIF('7天任务'!$B$5:$B$200,1),0) -> 0.72222222
A15: 产品付费与审核 | B15: =COUNTIF('7天任务'!$D$5:$D$200,A15) -> 9 | C15: =COUNTIFS('7天任务'!$D$5:$D$200,A15,'7天任务'!$H$5:$H$200,"已完成") -> 4 | D15: =COUNTIFS('7天任务'!$D$5:$D$200,A15,'7天任务'!$H$5:$H$200,"进行中")+COUNTIFS('7天任务'!$D$5:$D$200,A15,'7天任务'!$H$5:$H$200,"待审核") -> 1 | E15: =COUNTIFS('7天任务'!$D$5:$D$200,A15,'7天任务'!$H$5:$H$200,"已阻塞") -> 0 | F15: =IFERROR(SUMIF('7天任务'!$D$5:$D$200,A15,'7天任务'!$I$5:$I$200)/COUNTIF('7天任务'!$D$5:$D$200,A15),0) -> 0.5 | H15: 第2天 | I15: =$C$5+1 -> 46216 | J15: =COUNTIF('7天任务'!$B$5:$B$200,2) -> 13 | K15: =COUNTIFS('7天任务'!$B$5:$B$200,2,'7天任务'!$H$5:$H$200,"已完成") -> 6 | L15: =COUNTIFS('7天任务'!$B$5:$B$200,2,'7天任务'!$H$5:$H$200,"已阻塞") -> 0 | M15: =IFERROR(SUMIF('7天任务'!$B$5:$B$200,2,'7天任务'!$I$5:$I$200)/COUNTIF('7天任务'!$B$5:$B$200,2),0) -> 0.5
A16: 产品推广与内容 | B16: =COUNTIF('7天任务'!$D$5:$D$200,A16) -> 21 | C16: =COUNTIFS('7天任务'!$D$5:$D$200,A16,'7天任务'!$H$5:$H$200,"已完成") -> 4 | D16: =COUNTIFS('7天任务'!$D$5:$D$200,A16,'7天任务'!$H$5:$H$200,"进行中")+COUNTIFS('7天任务'!$D$5:$D$200,A16,'7天任务'!$H$5:$H$200,"待审核") -> 0 | E16: =COUNTIFS('7天任务'!$D$5:$D$200,A16,'7天任务'!$H$5:$H$200,"已阻塞") -> 0 | F16: =IFERROR(SUMIF('7天任务'!$D$5:$D$200,A16,'7天任务'!$I$5:$I$200)/COUNTIF('7天任务'!$D$5:$D$200,A16),0) -> 0.19047619 | H16: 第3天 | I16: =$C$5+2 -> 46217 | J16: =COUNTIF('7天任务'!$B$5:$B$200,3) -> 10 | K16: =COUNTIFS('7天任务'!$B$5:$B$200,3,'7天任务'!$H$5:$H$200,"已完成") -> 0 | L16: =COUNTIFS('7天任务'!$B$5:$B$200,3,'7天任务'!$H$5:$H$200,"已阻塞") -> 0 | M16: =IFERROR(SUMIF('7天任务'!$B$5:$B$200,3,'7天任务'!$I$5:$I$200)/COUNTIF('7天任务'!$B$5:$B$200,3),0) -> 0.05
A17: 用户测试与运营 | B17: =COUNTIF('7天任务'!$D$5:$D$200,A17) -> 8 | C17: =COUNTIFS('7天任务'!$D$5:$D$200,A17,'7天任务'!$H$5:$H$200,"已完成") -> 0 | D17: =COUNTIFS('7天任务'!$D$5:$D$200,A17,'7天任务'!$H$5:$H$200,"进行中")+COUNTIFS('7天任务'!$D$5:$D$200,A17,'7天任务'!$H$5:$H$200,"待审核") -> 0 | E17: =COUNTIFS('7天任务'!$D$5:$D$200,A17,'7天任务'!$H$5:$H$200,"已阻塞") -> 0 | F17: =IFERROR(SUMIF('7天任务'!$D$5:$D$200,A17,'7天任务'!$I$5:$I$200)/COUNTIF('7天任务'!$D$5:$D$200,A17),0) -> 0 | H17: 第4天 | I17: =$C$5+3 -> 46218 | J17: =COUNTIF('7天任务'!$B$5:$B$200,4) -> 9 | K17: =COUNTIFS('7天任务'!$B$5:$B$200,4,'7天任务'!$H$5:$H$200,"已完成") -> 0 | L17: =COUNTIFS('7天任务'!$B$5:$B$200,4,'7天任务'!$H$5:$H$200,"已阻塞") -> 0 | M17: =IFERROR(SUMIF('7天任务'!$B$5:$B$200,4,'7天任务'!$I$5:$I$200)/COUNTIF('7天任务'!$B$5:$B$200,4),0) -> 0.055555556
A18: 品牌与账号基础 | B18: =COUNTIF('7天任务'!$D$5:$D$200,A18) -> 6 | C18: =COUNTIFS('7天任务'!$D$5:$D$200,A18,'7天任务'!$H$5:$H$200,"已完成") -> 5 | D18: =COUNTIFS('7天任务'!$D$5:$D$200,A18,'7天任务'!$H$5:$H$200,"进行中")+COUNTIFS('7天任务'!$D$5:$D$200,A18,'7天任务'!$H$5:$H$200,"待审核") -> 1 | E18: =COUNTIFS('7天任务'!$D$5:$D$200,A18,'7天任务'!$H$5:$H$200,"已阻塞") -> 0 | F18: =IFERROR(SUMIF('7天任务'!$D$5:$D$200,A18,'7天任务'!$I$5:$I$200)/COUNTIF('7天任务'!$D$5:$D$200,A18),0) -> 0.91666667 | H18: 第5天 | I18: =$C$5+4 -> 46219 | J18: =COUNTIF('7天任务'!$B$5:$B$200,5) -> 8 | K18: =COUNTIFS('7天任务'!$B$5:$B$200,5,'7天任务'!$H$5:$H$200,"已完成") -> 0 | L18: =COUNTIFS('7天任务'!$B$5:$B$200,5,'7天任务'!$H$5:$H$200,"已阻塞") -> 0 | M18: =IFERROR(SUMIF('7天任务'!$B$5:$B$200,5,'7天任务'!$I$5:$I$200)/COUNTIF('7天任务'!$B$5:$B$200,5),0) -> 0
A19: 合规与风险 | B19: =COUNTIF('7天任务'!$D$5:$D$200,A19) -> 4 | C19: =COUNTIFS('7天任务'!$D$5:$D$200,A19,'7天任务'!$H$5:$H$200,"已完成") -> 3 | D19: =COUNTIFS('7天任务'!$D$5:$D$200,A19,'7天任务'!$H$5:$H$200,"进行中")+COUNTIFS('7天任务'!$D$5:$D$200,A19,'7天任务'!$H$5:$H$200,"待审核") -> 0 | E19: =COUNTIFS('7天任务'!$D$5:$D$200,A19,'7天任务'!$H$5:$H$200,"已阻塞") -> 0 | F19: =IFERROR(SUMIF('7天任务'!$D$5:$D$200,A19,'7天任务'!$I$5:$I$200)/COUNTIF('7天任务'!$D$5:$D$200,A19),0) -> 0.75 | H19: 第6天 | I19: =$C$5+5 -> 46220 | J19: =COUNTIF('7天任务'!$B$5:$B$200,6) -> 7 | K19: =COUNTIFS('7天任务'!$B$5:$B$200,6,'7天任务'!$H$5:$H$200,"已完成") -> 0 | L19: =COUNTIFS('7天任务'!$B$5:$B$200,6,'7天任务'!$H$5:$H$200,"已阻塞") -> 0 | M19: =IFERROR(SUMIF('7天任务'!$B$5:$B$200,6,'7天任务'!$I$5:$I$200)/COUNTIF('7天任务'!$B$5:$B$200,6),0) -> 0
A20: 测试与质量 | B20: =COUNTIF('7天任务'!$D$5:$D$200,A20) -> 3 | C20: =COUNTIFS('7天任务'!$D$5:$D$200,A20,'7天任务'!$H$5:$H$200,"已完成") -> 0 | D20: =COUNTIFS('7天任务'!$D$5:$D$200,A20,'7天任务'!$H$5:$H$200,"进行中")+COUNTIFS('7天任务'!$D$5:$D$200,A20,'7天任务'!$H$5:$H$200,"待审核") -> 0 | E20: =COUNTIFS('7天任务'!$D$5:$D$200,A20,'7天任务'!$H$5:$H$200,"已阻塞") -> 0 | F20: =IFERROR(SUMIF('7天任务'!$D$5:$D$200,A20,'7天任务'!$I$5:$I$200)/COUNTIF('7天任务'!$D$5:$D$200,A20),0) -> 0 | H20: 第7天 | I20: =$C$5+6 -> 46221 | J20: =COUNTIF('7天任务'!$B$5:$B$200,7) -> 7 | K20: =COUNTIFS('7天任务'!$B$5:$B$200,7,'7天任务'!$H$5:$H$200,"已完成") -> 0 | L20: =COUNTIFS('7天任务'!$B$5:$B$200,7,'7天任务'!$H$5:$H$200,"已阻塞") -> 0 | M20: =IFERROR(SUMIF('7天任务'!$B$5:$B$200,7,'7天任务'!$I$5:$I$200)/COUNTIF('7天任务'!$B$5:$B$200,7),0) -> 0
A21: 部署与运维 | B21: =COUNTIF('7天任务'!$D$5:$D$200,A21) -> 4 | C21: =COUNTIFS('7天任务'!$D$5:$D$200,A21,'7天任务'!$H$5:$H$200,"已完成") -> 0 | D21: =COUNTIFS('7天任务'!$D$5:$D$200,A21,'7天任务'!$H$5:$H$200,"进行中")+COUNTIFS('7天任务'!$D$5:$D$200,A21,'7天任务'!$H$5:$H$200,"待审核") -> 1 | E21: =COUNTIFS('7天任务'!$D$5:$D$200,A21,'7天任务'!$H$5:$H$200,"已阻塞") -> 0 | F21: =IFERROR(SUMIF('7天任务'!$D$5:$D$200,A21,'7天任务'!$I$5:$I$200)/COUNTIF('7天任务'!$D$5:$D$200,A21),0) -> 0.125
A23: 建议：原“7天任务”用于外部上线节奏；研发功能、自动测试、模拟对局和部署必须分别在新增工作表达到P0发布闸门。

Sheet 7天任务
A1: 7天海外版上线任务清单
A3: 只需重点维护：状态、实际完成日、卡点/问题、下一步动作、链接/备注。日期会根据总览中的开始日期自动计算。
A4: 编号 | B4: 天数 | C4: 日期 | D4: 分类 | E4: 任务 | F4: 交付/完成标准 | G4: 优先级 | H4: 状态 | I4: 自动进度 | J4: 外部依赖/等待对象 | K4: 负责人 | L4: 截止日 | M4: 实际完成日 | N4: 卡点/问题 | O4: 下一步动作 | P4: 链接/备注
A5: 1 | B5: 1 | C5: =总览!$C$5+B5-1 -> 46215 | D5: 品牌与账号基础 | E5: 确认英文产品名与统一品牌写法 | F5: 确定一个用于官网、社媒、Creem与itch.io的统一英文品牌名 | G5: P0 | H5: 已完成 | I5: =IF(H5="已完成",1,IF(H5="待审核",0.9,IF(H5="进行中",0.5,IF(H5="已阻塞",0.25,0)))) -> 1 | J5: 域名/商标检索 | K5: 我 | L5: =C5 -> 46215 | M5: 46215
A6: 2 | B6: 1 | C6: =总览!$C$5+B6-1 -> 46215 | D6: 品牌与账号基础 | E6: 注册产品域名 | F6: 域名已购买，可正常解析，续费信息已保存 | G6: P0 | H6: 已完成 | I6: =IF(H6="已完成",1,IF(H6="待审核",0.9,IF(H6="进行中",0.5,IF(H6="已阻塞",0.25,0)))) -> 1 | J6: 域名注册商 | K6: 我 | L6: =C6 -> 46215 | M6: 46215
A7: 3 | B7: 1 | C7: =总览!$C$5+B7-1 -> 46215 | D7: 品牌与账号基础 | E7: 配置HTTPS与基础DNS | F7: 官网域名可通过HTTPS访问，不出现证书错误 | G7: P0 | H7: 已完成 | I7: =IF(H7="已完成",1,IF(H7="待审核",0.9,IF(H7="进行中",0.5,IF(H7="已阻塞",0.25,0)))) -> 1 | J7: 域名注册商/托管平台 | K7: 我 | L7: =C7 -> 46215
A8: 4 | B8: 1 | C8: =总览!$C$5+B8-1 -> 46215 | D8: 品牌与账号基础 | E8: 配置客服邮箱 | F8: support@域名 邮箱可正常收发邮件 | G8: P0 | H8: 已完成 | I8: =IF(H8="已完成",1,IF(H8="待审核",0.9,IF(H8="进行中",0.5,IF(H8="已阻塞",0.25,0)))) -> 1 | J8: 邮箱服务商 | K8: 我 | L8: =C8 -> 46215
A9: 5 | B9: 1 | C9: =总览!$C$5+B9-1 -> 46215 | D9: 产品付费与审核 | E9: 注册Creem并创建商店 | F9: Creem后台可访问，商店名称与品牌一致 | G9: P0 | H9: 已完成 | I9: =IF(H9="已完成",1,IF(H9="待审核",0.9,IF(H9="进行中",0.5,IF(H9="已阻塞",0.25,0)))) -> 1 | J9: Creem | K9: 我 | L9: =C9 -> 46215
A10: 6 | B10: 1 | C10: =总览!$C$5+B10-1 -> 46215 | D10: 产品付费与审核 | E10: 确认个人入驻资料 | F10: 实名认证姓名、国家、税务居民信息与收款账户一致 | G10: P0 | H10: 已完成 | I10: =IF(H10="已完成",1,IF(H10="待审核",0.9,IF(H10="进行中",0.5,IF(H10="已阻塞",0.25,0)))) -> 1 | J10: 个人证件/支付宝 | K10: 我 | L10: =C10 -> 46215
A11: 7 | B11: 1 | C11: =总览!$C$5+B11-1 -> 46215 | D11: 产品付费与审核 | E11: 提交KYC/KYB认证 | F11: 认证已提交，后台显示审核中或已通过 | G11: P0 | H11: 已完成 | I11: =IF(H11="已完成",1,IF(H11="待审核",0.9,IF(H11="进行中",0.5,IF(H11="已阻塞",0.25,0)))) -> 1 | J11: Creem审核 | K11: 我 | L11: =C11 -> 46215
A12: 8 | B12: 1 | C12: =总览!$C$5+B12-1 -> 46215 | D12: 产品推广与内容 | E12: 注册TikTok账号 | F12: 账号注册成功，用户名已占用并记录 | G12: P1 | H12: 已完成 | I12: =IF(H12="已完成",1,IF(H12="待审核",0.9,IF(H12="进行中",0.5,IF(H12="已阻塞",0.25,0)))) -> 1 | J12: TikTok | K12: 我 | L12: =C12 -> 46215
A13: 9 | B13: 1 | C13: =总览!$C$5+B13-1 -> 46215 | D13: 产品推广与内容 | E13: 注册YouTube频道 | F13: 频道创建成功，Handle已占用并记录 | G13: P1 | H13: 已完成 | I13: =IF(H13="已完成",1,IF(H13="待审核",0.9,IF(H13="进行中",0.5,IF(H13="已阻塞",0.25,0)))) -> 1 | J13: YouTube | K13: 我 | L13: =C13 -> 46215
A14: 10 | B14: 1 | C14: =总览!$C$5+B14-1 -> 46215 | D14: 产品推广与内容 | E14: 注册X账号 | F14: 账号注册成功，用户名已占用并记录 | G14: P2 | H14: 未开始 | I14: =IF(H14="已完成",1,IF(H14="待审核",0.9,IF(H14="进行中",0.5,IF(H14="已阻塞",0.25,0)))) -> 0 | J14: X | K14: 我 | L14: =C14 -> 46215
A15: 11 | B15: 1 | C15: =总览!$C$5+B15-1 -> 46215 | D15: 产品推广与内容 | E15: 注册Reddit账号 | F15: 账号注册成功，完成基础安全设置 | G15: P1 | H15: 未开始 | I15: =IF(H15="已完成",1,IF(H15="待审核",0.9,IF(H15="进行中",0.5,IF(H15="已阻塞",0.25,0)))) -> 0 | J15: Reddit | K15: 我 | L15: =C15 -> 46215
A16: 12 | B16: 1 | C16: =总览!$C$5+B16-1 -> 46215 | D16: 产品推广与内容 | E16: 创建Discord服务器 | F16: 服务器创建成功，邀请链接可用 | G16: P1 | H16: 已完成 | I16: =IF(H16="已完成",1,IF(H16="待审核",0.9,IF(H16="进行中",0.5,IF(H16="已阻塞",0.25,0)))) -> 1 | J16: Discord | K16: 我 | L16: =C16 -> 46215
A17: 13 | B17: 1 | C17: =总览!$C$5+B17-1 -> 46215 | D17: 产品推广与内容 | E17: 注册itch.io账号 | F17: 账号可登录，已具备创建项目页权限 | G17: P1 | H17: 已完成 | I17: =IF(H17="已完成",1,IF(H17="待审核",0.9,IF(H17="进行中",0.5,IF(H17="已阻塞",0.25,0)))) -> 1 | J17: itch.io | K17: 我 | L17: =C17 -> 46215
A18: 14 | B18: 1 | C18: =总览!$C$5+B18-1 -> 46215 | D18: 品牌与账号基础 | E18: 锁定统一用户名 | F18: 各渠道用户名尽量一致，并在账号表中记录 | G18: P1 | H18: 已完成 | I18: =IF(H18="已完成",1,IF(H18="待审核",0.9,IF(H18="进行中",0.5,IF(H18="已阻塞",0.25,0)))) -> 1 | J18: 各平台账号 | K18: 我 | L18: =C18 -> 46215
... A56: 52 | B56: 7 | C56: =总览!$C$5+B56-1 -> 46221 | D56: 用户测试与运营 | E56: 完成上线复盘与下周决策 | F56: 汇总流量、试玩、付费意愿、审核状态和下周优先级 | G56: P0 | H56: 未开始 | I56: =IF(H56="已完成",1,IF(H56="待审核",0.9,IF(H56="进行中",0.5,IF(H56="已阻塞",0.25,0)))) -> 0 | J56: 数据与反馈 | K56: 我 | L56: =C56 -> 46221
A57: 53 | B57: 1 | C57: =总览!$C$5+B57-1 -> 46215 | D57: 产品开发与上线 | E57: 完成现有代码与需求差距审计 | F57: 按唯一工程基线形成已实现/缺失/冲突清单；明确登录、房间、API、AI、数据库与部署缺口 | G57: P0 | H57: 进行中 | I57: =IF(H57="已完成",1,IF(H57="待审核",0.9,IF(H57="进行中",0.5,IF(H57="已阻塞",0.25,0)))) -> 0.5 | J57: 需求文档/代码仓库 | K57: 我/Codex | L57: =C57 -> 46215 | N57: 当前功能约30%，缺口较多 | O57: 先完成代码审计 | P57: 详见“开发进度”
A58: 54 | B58: 1 | C58: =总览!$C$5+B58-1 -> 46215 | D58: 产品开发与上线 | E58: 建立Supabase开发环境 | F58: Supabase Auth/Postgres可连接；密钥分前端anon与服务端service role | G58: P0 | H58: 未开始 | I58: =IF(H58="已完成",1,IF(H58="待审核",0.9,IF(H58="进行中",0.5,IF(H58="已阻塞",0.25,0)))) -> 0 | J58: Supabase | K58: 我/Codex | L58: =C58 -> 46215 | O58: 创建项目并保存环境变量 | P58: 详见“部署方案”
A59: 55 | B59: 1 | C59: =总览!$C$5+B59-1 -> 46215 | D59: 部署与运维 | E59: 确定MVP部署架构 | F59: 明确Vercel前端、NestJS后端、Supabase数据库/Auth、LLM和Creem的部署方式 | G59: P0 | H59: 进行中 | I59: =IF(H59="已完成",1,IF(H59="待审核",0.9,IF(H59="进行中",0.5,IF(H59="已阻塞",0.25,0)))) -> 0.5 | J59: Vercel/Railway/Supabase | K59: 我 | L59: =C59 -> 46215 | O59: 确认后端是否部署Railway | P59: 详见“部署方案”
A60: 56 | B60: 2 | C60: =总览!$C$5+B60-1 -> 46216 | D60: 产品开发与上线 | E60: 实现登录/注册与会话恢复 | F60: 邮箱登录可用；刷新、退出、重新登录和受保护路由正常 | G60: P0 | H60: 未开始 | I60: =IF(H60="已完成",1,IF(H60="待审核",0.9,IF(H60="进行中",0.5,IF(H60="已阻塞",0.25,0)))) -> 0 | J60: Supabase Auth | K60: Codex | L60: =C60 -> 46216 | N60: 当前缺少登录 | O60: 实现Magic Link/OTP与路由保护 | P60: 详见“开发进度”
A61: 57 | B61: 2 | C61: =总览!$C$5+B61-1 -> 46216 | D61: 产品开发与上线 | E61: 实现创建故事局/开启房间 | F61: 登录后可创建StoryRun并跳转 /game?runId；双击不重复创建 | G61: P0 | H61: 未开始 | I61: =IF(H61="已完成",1,IF(H61="待审核",0.9,IF(H61="进行中",0.5,IF(H61="已阻塞",0.25,0)))) -> 0 | J61: 登录/StoryRun API | K61: Codex | L61: =C61 -> 46216 | N61: 当前缺少开启房间 | O61: 实现POST /api/v4/story-runs | P61: 详见“开发进度”
A62: 58 | B62: 2 | C62: =总览!$C$5+B62-1 -> 46216 | D62: 产品开发与上线 | E62: 实现进入与恢复房间 | F62: 输入runId或“继续游戏”可恢复；无效和越权runId明确拒绝 | G62: P0 | H62: 未开始 | I62: =IF(H62="已完成",1,IF(H62="待审核",0.9,IF(H62="进行中",0.5,IF(H62="已阻塞",0.25,0)))) -> 0 | J62: 登录/GET run | K62: Codex | L62: =C62 -> 46216 | N62: 当前缺少进入房间 | O62: 实现我的游戏与恢复入口 | P62: 详见“开发进度”
A63: 59 | B63: 2 | C63: =总览!$C$5+B63-1 -> 46216 | D63: 产品开发与上线 | E63: 数据库化StoryRun/StoryEvent/AiTask | F63: 运行态进入Supabase PostgreSQL；浏览器只保存runId和非权威UI状态 | G63: P0 | H63: 未开始 | I63: =IF(H63="已完成",1,IF(H63="待审核",0.9,IF(H63="进行中",0.5,IF(H63="已阻塞",0.25,0)))) -> 0 | J63: Supabase/Prisma | K63: Codex | L63: =C63 -> 46216 | O63: 执行Schema与迁移 | P63: 详见“开发进度”
A64: 60 | B64: 3 | C64: =总览!$C$5+B64-1 -> 46217 | D64: 产品开发与上线 | E64: 完成v4核心API闭环 | F64: stories/roles/create/get/messages/dashboard/decision/maneuver/advance/finalize可用 | G64: P0 | H64: 未开始 | I64: =IF(H64="已完成",1,IF(H64="待审核",0.9,IF(H64="进行中",0.5,IF(H64="已阻塞",0.25,0)))) -> 0 | J64: NestJS/数据库 | K64: Codex | L64: =C64 -> 46217 | O64: 按API契约逐个实现 | P64: 详见“开发进度”
A65: 61 | B65: 3 | C65: =总览!$C$5+B65-1 -> 46217 | D65: 产品开发与上线 | E65: 完成主游戏8种UI状态接入 | F65: 单路由、固定三栏、持续叙事、决策、推演、变化、记录、弹窗和谋划全部接真实状态 | G65: P0 | H65: 进行中 | I65: =IF(H65="已完成",1,IF(H65="待审核",0.9,IF(H65="进行中",0.5,IF(H65="已阻塞",0.25,0)))) -> 0.5 | J65: v4 API/现有UI | K65: Codex | L65: =C65 -> 46217 | N65: UI已有设计但功能未闭环 | O65: 按状态机接入真实数据 | P65: 详见“开发进度”
A66: 62 | B66: 3 | C66: =总览!$C$5+B66-1 -> 46217 | D66: 产品开发与上线 | E66: 实现主线决策与ActionGuard | F66: A/B/C回填、1-200字、越权拦截、规则补丁、幂等与version冲突正常 | G66: P0 | H66: 未开始 | I66: =IF(H66="已完成",1,IF(H66="待审核",0.9,IF(H66="进行中",0.5,IF(H66="已阻塞",0.25,0)))) -> 0 | J66: 规则引擎/API | K66: Codex | L66: =C66 -> 46217 | O66: 先完成预设选项，再接自定义Guard | P66: 详见“开发进度”
A67: 63 | B67: 3 | C67: =总览!$C$5+B67-1 -> 46217 | D67: 产品开发与上线 | E67: 实现主动谋划与关键事件 | F67: 每日2次谋划；接触/调查/筹码/自拟；关键事件立即或稍后处理 | G67: P0 | H67: 未开始 | I67: =IF(H67="已完成",1,IF(H67="待审核",0.9,IF(H67="进行中",0.5,IF(H67="已阻塞",0.25,0)))) -> 0 | J67: 规则引擎/API | K67: Codex | L67: =C67 -> 46217 | O67: 实现计数、跨日重置和defer | P67: 详见“开发进度”
A68: 64 | B68: 4 | C68: =总览!$C$5+B68-1 -> 46218 | D68: 产品开发与上线 | E68: 接入AI结构化输出与Fallback | F68: 真实模型输出Schema校验；超时重试1次；双失败规则Fallback完成落账 | G68: P0 | H68: 未开始 | I68: =IF(H68="已完成",1,IF(H68="待审核",0.9,IF(H68="进行中",0.5,IF(H68="已阻塞",0.25,0)))) -> 0 | J68: LLM/AiTask | K68: Codex | L68: =C68 -> 46218 | O68: 先mock后真实模型 | P68: 详见“开发进度”
A69: 65 | B69: 4 | C69: =总览!$C$5+B69-1 -> 46218 | D69: 产品付费与审核 | E69: 跑通Creem Test支付闭环 | F69: 创建Checkout、Webhook签名、重复通知幂等、支付后权益可见 | G69: P0 | H69: 进行中 | I69: =IF(H69="已完成",1,IF(H69="待审核",0.9,IF(H69="进行中",0.5,IF(H69="已阻塞",0.25,0)))) -> 0.5 | J69: Creem/公网API | K69: 我/Codex | L69: =C69 -> 46218 | N69: Webhook与密钥仍需完整验证 | O69: 完成Test Mode端到端支付 | P69: 详见“开发进度/部署方案”
A70: 66 | B70: 4 | C70: =总览!$C$5+B70-1 -> 46218 | D70: 产品开发与上线 | E70: 实现日志、埋点与安全隔离 | F70: 结构化日志、核心漏斗埋点、RLS/CORS、HTML转义和私密字段扫描生效 | G70: P0 | H70: 未开始 | I70: =IF(H70="已完成",1,IF(H70="待审核",0.9,IF(H70="进行中",0.5,IF(H70="已阻塞",0.25,0)))) -> 0 | J70: API/前端/Supabase | K70: Codex | L70: =C70 -> 46218 | O70: 先做P0安全和错误日志 | P70: 详见“开发进度”
A71: 67 | B71: 5 | C71: =总览!$C$5+B71-1 -> 46219 | D71: 测试与质量 | E71: 完成P0自动化测试 | F71: 功能、Guard、因果、信息隔离、并发、恢复与UI的P0用例全部通过 | G71: P0 | H71: 未开始 | I71: =IF(H71="已完成",1,IF(H71="待审核",0.9,IF(H71="进行中",0.5,IF(H71="已阻塞",0.25,0)))) -> 0 | J71: 测试脚本/CI | K71: Codex | L71: =C71 -> 46219 | N71: 当前缺少系统测试 | O71: 按“测试进度”逐项执行 | P71: 详见“测试进度”
A72: 68 | B72: 5 | C72: =总览!$C$5+B72-1 -> 46219 | D72: 测试与质量 | E72: 完成至少20局模拟测试 | F72: 覆盖A/B/C/Mixed、0/1/2谋划、关键事件、AI故障、刷新和并发 | G72: P0 | H72: 未开始 | I72: =IF(H72="已完成",1,IF(H72="待审核",0.9,IF(H72="进行中",0.5,IF(H72="已阻塞",0.25,0)))) -> 0 | J72: staging/mock/真实模型 | K72: Codex/我 | L72: =C72 -> 46219 | N72: 当前缺少模拟测试 | O72: 先自动模拟，再人工试玩 | P72: 详见“模拟对局”
A73: 69 | B73: 5 | C73: =总览!$C$5+B73-1 -> 46219 | D73: 测试与质量 | E73: 完成安全与信息隔离检查 | F73: 用户越权、前台私密字段、HTML注入、密钥泄露和日志脱敏全部通过 | G73: P0 | H73: 未开始 | I73: =IF(H73="已完成",1,IF(H73="待审核",0.9,IF(H73="进行中",0.5,IF(H73="已阻塞",0.25,0)))) -> 0 | J73: 安全扫描/HTTP | K73: Codex | L73: =C73 -> 46219 | O73: 执行I类、AUTH和DEP安全用例 | P73: 详见“测试进度”
A74: 70 | B74: 6 | C74: =总览!$C$5+B74-1 -> 46220 | D74: 部署与运维 | E74: 部署staging环境 | F74: Vercel Web、API、Supabase、Creem Test、真实AI与Fallback独立可用 | G74: P0 | H74: 未开始 | I74: =IF(H74="已完成",1,IF(H74="待审核",0.9,IF(H74="进行中",0.5,IF(H74="已阻塞",0.25,0)))) -> 0 | J74: Vercel/Railway/Supabase | K74: 我/Codex | L74: =C74 -> 46220 | O74: 按部署任务表配置 | P74: 详见“部署方案”
A75: 71 | B75: 6 | C75: =总览!$C$5+B75-1 -> 46220 | D75: 部署与运维 | E75: 完成冒烟、备份、监控和回滚演练 | F75: staging端到端通过；备份可恢复；日志告警和上一版本回滚可用 | G75: P0 | H75: 未开始 | I75: =IF(H75="已完成",1,IF(H75="待审核",0.9,IF(H75="进行中",0.5,IF(H75="已阻塞",0.25,0)))) -> 0 | J75: staging/监控 | K75: 我/Codex | L75: =C75 -> 46220 | O75: 执行DEP用例 | P75: 详见“部署方案/测试进度”
A76: 72 | B76: 7 | C76: =总览!$C$5+B76-1 -> 46221 | D76: 部署与运维 | E76: 生产部署与最终发布闸门 | F76: P0开发完成、P0测试通过、20局无死路、生产冒烟通过后才公开Beta | G76: P0 | H76: 未开始 | I76: =IF(H76="已完成",1,IF(H76="待审核",0.9,IF(H76="进行中",0.5,IF(H76="已阻塞",0.25,0)))) -> 0 | J76: 全部前置 | K76: 我/Codex | L76: =C76 -> 46221 | O76: 完成发布评审并记录版本 | P76: 详见“研发总览/上线验收”

Sheet 账号与外部依赖
A1: 账号、审核与外部依赖追踪
A3: 将所有会卡住上线的外部事项集中记录：账号、审核、域名、邮箱、政策页、创作者和社区。
A4: 类型 | B4: 平台/事项 | C4: 用途 | D4: 目标用户名/名称 | E4: 注册状态 | F4: 资料完善 | G4: 审核状态 | H4: URL/入口 | I4: 下一步 | J4: 备注
A5: 基础设施 | B5: 产品域名 | C5: 官网与品牌入口 | E5: 已完成 | F5: 未开始 | G5: 不适用 | I5: 注册并解析
A6: 基础设施 | B6: 客服邮箱 | C6: Creem审核与用户支持 | D6: support@你的域名 | E6: 已完成 | F6: 未开始 | G6: 不适用 | I6: 配置收发与签名
A7: 支付审核 | B7: Creem | C7: 海外收款与税务处理 | E7: 已注册 | F7: 进行中 | G7: 待审核 | I7: 完成KYC/审核 | J7: 当前处于测试模式
A8: 推广账号 | B8: TikTok | C8: 短视频自然流量 | E8: 未开始 | F8: 未开始 | G8: 不适用 | I8: 注册并锁定用户名
A9: 推广账号 | B9: YouTube | C9: Shorts与长期内容 | E9: 未开始 | F9: 未开始 | G9: 不适用 | I9: 创建频道
A10: 推广账号 | B10: X | C10: 开发者传播与更新 | E10: 未开始 | F10: 未开始 | G10: 不适用 | I10: 注册并完善资料
A11: 推广账号 | B11: Reddit | C11: 高意愿测试用户 | E11: 未开始 | F11: 未开始 | G11: 不适用 | I11: 注册并观察社区规则
A12: 社区运营 | B12: Discord | C12: 测试组织与长期社群 | E12: 未开始 | F12: 未开始 | G12: 不适用 | I12: 创建服务器和频道
A13: 游戏平台 | B13: itch.io | C13: 浏览器游戏展示与可信度 | E13: 未开始 | F13: 未开始 | G13: 待审核 | I13: 创建项目草稿
A14: 合规页面 | B14: Privacy Policy | C14: 数据与隐私说明 | E14: 未开始 | F14: 未开始 | G14: 不适用 | I14: 发布并链接到页脚
A15: 合规页面 | B15: Terms of Service | C15: 用户规则与责任边界 | E15: 未开始 | F15: 未开始 | G15: 不适用 | I15: 发布并链接到页脚
A16: 合规页面 | B16: Refund Policy | C16: 退款条件和处理时限 | E16: 未开始 | F16: 未开始 | G16: 不适用 | I16: 发布并链接到页脚
A17: 推广资源 | B17: 小型内容创作者 | C17: 试玩与内容合作 | E17: 未开始 | F17: 未开始 | G17: 待联系 | I17: 建立名单并逐一联系
A18: 推广资源 | B18: 目标社区清单 | C18: Reddit/Discord/TTRPG/AI游戏 | E18: 未开始 | F18: 未开始 | G18: 待研究 | I18: 记录规则和发帖窗口

Sheet 上线验收
A1: 海外 Limited Beta 上线验收清单
A3: 只有“上线必须项”全部完成或有明确备用方案时，才执行第7天公开发布。
A4: 分类 | B4: 验收项 | C4: 完成标准 | D4: 是否必须 | E4: 状态 | F4: 证据/链接 | G4: 负责人 | H4: 备注
A5: 基础设施 | B5: 独立域名与HTTPS | C5: 官网通过HTTPS稳定访问 | D5: 必须 | E5: 已完成 | G5: 我
A6: 基础设施 | B6: 客服邮箱可用 | C6: support@域名 可正常收发 | D6: 必须 | E6: 已完成 | G6: 我
A7: 网站 | B7: 英文首页已上线 | C7: 价值主张、试玩入口、价格清晰 | D7: 必须 | E7: 未开始 | G7: 我
A8: 网站 | B8: 移动端可访问 | C8: 手机浏览不影响阅读和转化 | D8: 必须 | E8: 未开始 | G8: 我
A9: 合规 | B9: Privacy Policy | C9: 页面公开且页脚可访问 | D9: 必须 | E9: 已完成 | G9: 我
A10: 合规 | B10: Terms of Service | C10: 页面公开且页脚可访问 | D10: 必须 | E10: 已完成 | G10: 我
A11: 合规 | B11: Refund Policy | C11: 页面公开且价格页可访问 | D11: 必须 | E11: 已完成 | G11: 我
A12: 支付 | B12: Creem KYC已提交 | C12: 后台显示审核中或已通过 | D12: 必须 | E12: 未开始 | G12: 我
A13: 支付 | B13: Creem真实收款可用或有备用方案 | C13: Live支付可用；否则Founder候补可用 | D13: 必须 | E13: 未开始 | G13: 我
A14: 支付 | B14: 商品名称与价格一致 | C14: 官网、Creem与退款政策描述一致 | D14: 必须 | E14: 未开始 | G14: 我
A15: 推广 | B15: 至少5条短视频已准备 | C15: 可直接发布，含统一落地页链接 | D15: 必须 | E15: 未开始 | G15: 我
A16: 推广 | B16: 主要社媒账号可用 | C16: TikTok、YouTube至少已注册并完善 | D16: 必须 | E16: 未开始 | G16: 我
... A22: 备用方案 | B22: Creem未通过时不阻塞上线 | C22: 免费Beta+Founder候补入口已测试 | D22: 必须 | E22: 未开始 | G22: 我
A23: 账号 | B23: 用户登录与会话恢复 | C23: 邮箱登录可用；刷新与重新登录可恢复账号和历史故事局 | D23: 必须 | E23: 未开始 | G23: 我/Codex | H23: 缺少登录时不能形成付费账号闭环
A24: 核心功能 | B24: 创建故事局/开启房间 | C24: 登录后可创建StoryRun并进入/game?runId | D24: 必须 | E24: 未开始 | G24: Codex | H24: 幂等创建，不重复产生房间
A25: 核心功能 | B25: 进入与恢复房间 | C25: 有效runId可恢复；无效/越权runId明确拒绝 | D25: 必须 | E25: 未开始 | G25: Codex | H25: 浏览器不保存权威状态
A26: 核心功能 | B26: 7天主线闭环 | C26: 第1-6天共12次主线决策，第7天完成全局与个人结局 | D26: 必须 | E26: 未开始 | G26: Codex | H26: 至少一条完整路径通过
A27: 核心功能 | B27: 主动谋划与关键事件 | C27: 每天最多2次谋划；关键事件可立即/稍后并正确计数 | D27: 必须 | E27: 未开始 | G27: Codex | H27: 不替代主线决策
A28: AI稳定性 | B28: AI重试与规则Fallback | C28: AI连续失败时仍能正常落账和完成一局，用户不见技术错误 | D28: 必须 | E28: 未开始 | G28: Codex | H28: fallback失败才显示可恢复错误
A29: 数据安全 | B29: 登录权限与私密字段隔离 | C29: 用户不能读取他人局；公共响应无隐藏推理、内部收益风险和密钥 | D29: 必须 | E29: 未开始 | G29: Codex | H29: 安全扫描必须通过
A30: 测试 | B30: P0自动化测试通过 | C30: 功能、ActionGuard、并发、恢复、UI与信息隔离P0用例100%通过 | D30: 必须 | E30: 未开始 | G30: Codex | H30: 详见“测试进度”
A31: 测试 | B31: 20局连续模拟通过 | C31: A/B/C/Mixed、0/1/2谋划、故障恢复均无死路 | D31: 必须 | E31: 未开始 | G31: Codex | H31: 详见“模拟对局”
A32: 部署 | B32: Staging完整可用 | C32: 独立数据库、Creem Test、真实模型+fallback、日志与告警可用 | D32: 必须 | E32: 未开始 | G32: 我/Codex | H32: 不能与production共享密钥
A33: 部署 | B33: Production部署与备份 | C33: Web、API、Supabase、域名、迁移、备份、回滚和Health Check完成 | D33: 必须 | E33: 未开始 | G33: 我/Codex | H33: 详见“部署方案”
A34: 上线闸门 | B34: 生产冒烟与回滚演练 | C34: 首页→登录→创建局→决策→刷新恢复→支付/候补全链路通过 | D34: 必须 | E34: 未开始 | G34: 我/Codex | H34: 失败则停止公开发布

Sheet 开发进度
A1: AI多人剧情推演｜MVP开发进度
A3: 核验更新（2026-07-15）：已按当前代码、自动化测试与 Railway test 运行状态回填。已完成代表当前代码/测试证据成立；待审核代表实现已具备但 Vercel 正式发布、完整视觉验收或 Creem Dashboard 证据尚未闭环。
A4: 编号 | B4: 模块 | C4: 子模块 | D4: 功能/任务 | E4: 实现说明 | F4: 交付/验收标准 | G4: 需求依据 | H4: 优先级 | I4: 上线阻断 | J4: 状态 | K4: 自动进度 | L4: 前置依赖 | M4: 建议阶段 | N4: 负责人 | O4: 计划完成日 | P4: 实际完成日 | Q4: 卡点/问题 | R4: 下一步动作 | S4: 证据/链接
A5: DEV-001 | B5: 工程基线 | C5: 仓库审计 | D5: 核对现有代码与唯一工程基线 | E5: 盘点 apps/web、apps/api、packages/shared、packages/templates、Prisma 和现有分支，形成“已实现/缺失/冲突”清单。 | F5: 清单覆盖登录、入口、StoryRun、8种UI状态、AI、数据库、测试和部署；所有冲突有处理结论。 | G5: 01基线§1-2；07 PRD§18 | H5: P0 | I5: 是 | J5: 已完成 | K5: =IF(J5="不适用","",IF(J5="已完成",1,IF(J5="待审核",0.9,IF(J5="进行中",0.5,IF(J5="已阻塞",0.25,0))))) -> 1 | M5: 第1天 | N5: Codex+我 | O5: =总览!$C$5+0 -> 46215 | Q5: 2026-07-15：已按当前仓库、脚本与测试复核。 | R5: 随需求变化维护基线与契约。 | S5: pnpm test:api、pnpm --filter @apps/web typecheck、pnpm lint:config 均通过。
A6: DEV-002 | B6: 工程基线 | C6: 范围锁定 | D6: 锁定 Web 单人 MVP 范围 | E6: 当前只做《桑田诏》、浙江总督、7天、12次主线决策、每日2次谋划；真人多人仅预留。 | F6: 代码、页面和接口不存在同时开发真人多人/小程序/两套前端的分叉。 | G6: 01基线§2；07 PRD§3 | H6: P0 | I6: 是 | J6: 不适用 | K6: =IF(J6="不适用","",IF(J6="已完成",1,IF(J6="待审核",0.9,IF(J6="进行中",0.5,IF(J6="已阻塞",0.25,0))))) | L6: 代码审计 | M6: 第1天 | N6: 我 | O6: =总览!$C$5+0 -> 46215 | Q6: 原表限定单人MVP/禁止真人多人；现行代码已演进为房间与多用户实现，原验收口径不再适用。 | R6: 后续以 v1.4 房间/多用户范围重建对应任务与验收口径。 | S6: apps/api/src/rooms.controller.ts；docs/auto-execute/many-worlds-v14-p0-closeout-final-acceptance-gate.md
A7: DEV-003 | B7: 工程基线 | C7: 前端基线 | D7: 确认 apps/web 为唯一正式前端 | E7: 沿用现有 apps/web，不新建 player-web，不在本轮迁移技术栈。 | F7: 构建与部署只产出一套正式 Web；路由符合基线。 | G7: 01基线§5 | H7: P0 | I7: 是 | J7: 已完成 | K7: =IF(J7="不适用","",IF(J7="已完成",1,IF(J7="待审核",0.9,IF(J7="进行中",0.5,IF(J7="已阻塞",0.25,0))))) -> 1 | L7: 代码审计 | M7: 第1天 | N7: Codex | O7: =总览!$C$5+0 -> 46215 | Q7: 2026-07-15：已按当前仓库、脚本与测试复核。 | R7: 随需求变化维护基线与契约。 | S7: pnpm test:api、pnpm --filter @apps/web typecheck、pnpm lint:config 均通过。
A8: DEV-004 | B8: 工程基线 | C8: 后端基线 | D8: 确认 apps/api NestJS 与 /api/v4 | E8: 统一 API 前缀、异常格式、共享类型和请求校验。 | F8: 健康检查与 v4 路由可访问，旧接口仅在适配层保留。 | G8: 01基线§6；02状态机§9 | H8: P0 | I8: 是 | J8: 已完成 | K8: =IF(J8="不适用","",IF(J8="已完成",1,IF(J8="待审核",0.9,IF(J8="进行中",0.5,IF(J8="已阻塞",0.25,0))))) -> 1 | L8: 代码审计 | M8: 第1天 | N8: Codex | O8: =总览!$C$5+0 -> 46215 | Q8: 2026-07-15：已按当前仓库、脚本与测试复核。 | R8: 随需求变化维护基线与契约。 | S8: pnpm test:api、pnpm --filter @apps/web typecheck、pnpm lint:config 均通过。
A9: DEV-005 | B9: 工程基线 | C9: 共享契约 | D9: 统一字段与共享类型 | E9: 统一 templateKey、selectedRoleKey、runId、eventId、version、optionKey、customText、maneuverType 等字段。 | F9: 前后端编译通过；新接口无 storyId/templateId/messageId 混用。 | G9: 01基线§6.2；02状态机§1 | H9: P0 | I9: 是 | J9: 已完成 | K9: =IF(J9="不适用","",IF(J9="已完成",1,IF(J9="待审核",0.9,IF(J9="进行中",0.5,IF(J9="已阻塞",0.25,0))))) -> 1 | L9: 后端基线 | M9: 第1天 | N9: Codex | O9: =总览!$C$5+0 -> 46215 | Q9: 2026-07-15：已按当前仓库、脚本与测试复核。 | R9: 随需求变化维护基线与契约。 | S9: pnpm test:api、pnpm --filter @apps/web typecheck、pnpm lint:config 均通过。
A10: DEV-006 | B10: 工程基线 | C10: 配置校验 | D10: 接入剧本 JSON Schema 与跨文件 lint | E10: 将 Markdown 剧本编译为 story/roles/days/decisions/maneuvers/leverage/endings/context-cards JSON，并用 AJV 校验。 | F10: 构建时能发现缺失角色、无效变量、超过12个决策、不可达结局、公共字段泄露。 | G10: 03 Schema§1-12 | H10: P0 | I10: 是 | J10: 已完成 | K10: =IF(J10="不适用","",IF(J10="已完成",1,IF(J10="待审核",0.9,IF(J10="进行中",0.5,IF(J10="已阻塞",0.25,0))))) -> 1 | L10: 共享契约 | M10: 第2天 | N10: Codex | O10: =总览!$C$5+1 -> 46216 | Q10: 2026-07-15：已按当前仓库、脚本与测试复核。 | R10: 随需求变化维护基线与契约。 | S10: pnpm test:api、pnpm --filter @apps/web typecheck、pnpm lint:config 均通过。
A11: DEV-007 | B11: 工程基线 | C11: 构建命令 | D11: 统一本地与 CI 命令 | E11: 配置 install、typecheck、config lint、unit、service、HTTP、E2E 和安全投影测试命令。 | F11: README/脚本可一键执行；失败会阻止发布。 | G11: 04验收§11 | H11: P0 | I11: 是 | J11: 进行中 | K11: =IF(J11="不适用","",IF(J11="已完成",1,IF(J11="待审核",0.9,IF(J11="进行中",0.5,IF(J11="已阻塞",0.25,0))))) -> 0.5 | L11: 配置校验 | M11: 第5天 | N11: Codex | O11: =总览!$C$5+4 -> 46219 | Q11: 本地命令已具备并通过本轮核验；CI 发布闸门未取得当前远端证据。 | R11: 补充 CI 执行记录与失败阻断证明。 | S11: package.json scripts；本轮本地校验通过。
A12: DEV-008 | B12: 工程基线 | C12: 环境分层 | D12: 建立 local/test/staging/production 配置 | E12: 四套环境数据、密钥、AI预算隔离；测试使用固定 mock。 | F12: staging 与 production 不共用数据库、密钥和预算。 | G12: 05部署§1 | H12: P0 | I12: 是 | J12: 进行中 | K12: =IF(J12="不适用","",IF(J12="已完成",1,IF(J12="待审核",0.9,IF(J12="进行中",0.5,IF(J12="已阻塞",0.25,0))))) -> 0.5 | M12: 第1天 | N12: Codex+我 | O12: =总览!$C$5+0 -> 46215 | Q12: local 与 Railway test 已核验；staging/production 与密钥隔离尚未验证。 | R12: 完成 Vercel/生产 API 域名、生产数据库与 Creem live 环境分层。 | S12: Railway test /api/health、/api/health/ready 均为 200。
A13: DEV-009 | B13: 登录与账号 | C13: Supabase | D13: 创建 Supabase 项目 | E13: 启用 PostgreSQL 与 Auth，选择与目标用户接近的区域，记录项目URL和密钥。 | F13: 开发环境可连接；anon key 仅前端使用，service role 仅服务端使用。 | G13: 用户新增要求；08数据库§4-5 | H13: P0 | I13: 是 | J13: 已完成 | K13: =IF(J13="不适用","",IF(J13="已完成",1,IF(J13="待审核",0.9,IF(J13="进行中",0.5,IF(J13="已阻塞",0.25,0))))) -> 1 | L13: 环境分层 | M13: 第1天 | N13: 我 | O13: =总览!$C$5+0 -> 46215 | Q13: 当前实现与测试环境已存在；关键 API 需要身份验证。 | R13: 保留生产环境的人工验证。 | S13: prisma/schema.prisma；apps/api/src/auth；apps/api/src/api-transport.ts
A14: DEV-010 | B14: 登录与账号 | C14: 数据模型 | D14: 建立 profiles 与用户关联 | E14: 新增 profiles/user_id；StoryRun.userId 与登录用户关联。 | F14: 用户只能读取自己的 StoryRun；数据库存在索引和外键策略。 | G14: 01基线§4.1；08数据库§6 | H14: P0 | I14: 是 | J14: 进行中 | K14: =IF(J14="不适用","",IF(J14="已完成",1,IF(J14="待审核",0.9,IF(J14="进行中",0.5,IF(J14="已阻塞",0.25,0))))) -> 0.5 | L14: Supabase项目 | M14: 第2天 | N14: Codex | O14: =总览!$C$5+1 -> 46216 | Q14: 用户、会话与房间恢复代码已存在，但原表的 Supabase profiles/自动刷新/历史列表口径尚未完整逐项验收。 | R14: 按现行账户模型补充真实浏览器验收。 | S14: apps/api/src/auth；apps/api/src/rooms.service.ts；apps/web/public/platform.js
A15: DEV-011 | B15: 登录与账号 | C15: 登录页 | D15: 实现英文登录/注册页面 | E15: 支持邮箱验证码或 Magic Link；提供错误、发送中、已发送状态。 | F15: 新用户可完成登录，错误邮箱和频率限制有明确提示。 | G15: 用户新增要求 | H15: P0 | I15: 是 | J15: 已完成 | K15: =IF(J15="不适用","",IF(J15="已完成",1,IF(J15="待审核",0.9,IF(J15="进行中",0.5,IF(J15="已阻塞",0.25,0))))) -> 1 | L15: Supabase项目 | M15: 第2天 | N15: Codex | O15: =总览!$C$5+1 -> 46216 | Q15: 当前实现与测试环境已存在；关键 API 需要身份验证。 | R15: 保留生产环境的人工验证。 | S15: prisma/schema.prisma；apps/api/src/auth；apps/api/src/api-transport.ts
A16: DEV-012 | B16: 登录与账号 | C16: 会话 | D16: 实现会话持久化与自动刷新 | E16: 页面刷新、关闭重开后恢复登录；token 过期自动刷新。 | F16: 刷新后不丢失登录；失效会话跳转登录并保留返回地址。 | G16: 用户新增要求 | H16: P0 | I16: 是 | J16: 进行中 | K16: =IF(J16="不适用","",IF(J16="已完成",1,IF(J16="待审核",0.9,IF(J16="进行中",0.5,IF(J16="已阻塞",0.25,0))))) -> 0.5 | L16: 登录页 | M16: 第2天 | N16: Codex | O16: =总览!$C$5+1 -> 46216 | Q16: 用户、会话与房间恢复代码已存在，但原表的 Supabase profiles/自动刷新/历史列表口径尚未完整逐项验收。 | R16: 按现行账户模型补充真实浏览器验收。 | S16: apps/api/src/auth；apps/api/src/rooms.service.ts；apps/web/public/platform.js
A17: DEV-013 | B17: 登录与账号 | C17: 路由保护 | D17: 保护创建局、我的游戏与支付页面 | E17: 未登录用户访问受保护路由时跳转登录；公开首页和法律页面不受影响。 | F17: 受保护 API 同时验证用户身份，不能只依赖前端。 | G17: 用户新增要求；08数据库§16 | H17: P0 | I17: 是 | J17: 已完成 | K17: =IF(J17="不适用","",IF(J17="已完成",1,IF(J17="待审核",0.9,IF(J17="进行中",0.5,IF(J17="已阻塞",0.25,0))))) -> 1 | L17: 会话 | M17: 第2天 | N17: Codex | O17: =总览!$C$5+1 -> 46216 | Q17: 当前实现与测试环境已存在；关键 API 需要身份验证。 | R17: 保留生产环境的人工验证。 | S17: prisma/schema.prisma；apps/api/src/auth；apps/api/src/api-transport.ts
A18: DEV-014 | B18: 登录与账号 | C18: 退出 | D18: 实现退出登录 | E18: 清理本地会话和非权威草稿，返回首页。 | F18: 退出后无法继续调用用户私有 API；再次登录可恢复历史局。 | G18: 用户新增要求 | H18: P0 | I18: 否 | J18: 未开始 | K18: =IF(J18="不适用","",IF(J18="已完成",1,IF(J18="待审核",0.9,IF(J18="进行中",0.5,IF(J18="已阻塞",0.25,0))))) -> 0 | L18: 会话 | M18: 第2天 | N18: Codex | O18: =总览!$C$5+1 -> 46216
A19: DEV-015 | B19: 登录与账号 | C19: 我的游戏 | D19: 实现最近故事局列表 | E19: 展示进行中、已完成、创建时间、当前天数和继续按钮。 | F19: 登录用户可继续自己的局；无法看到其他用户局。 | G19: 用户新增要求；08数据库§6 | H19: P0 | I19: 是 | J19: 进行中 | K19: =IF(J19="不适用","",IF(J19="已完成",1,IF(J19="待审核",0.9,IF(J19="进行中",0.5,IF(J19="已阻塞",0.25,0))))) -> 0.5 | L19: profiles与StoryRun | M19: 第3天 | N19: Codex | O19: =总览!$C$5+2 -> 46217 | Q19: 用户、会话与房间恢复代码已存在，但原表的 Supabase profiles/自动刷新/历史列表口径尚未完整逐项验收。 | R19: 按现行账户模型补充真实浏览器验收。 | S19: apps/api/src/auth；apps/api/src/rooms.service.ts；apps/web/public/platform.js
A20: DEV-016 | B20: 登录与账号 | C20: 账户页 | D20: 实现基础账户与客服入口 | E20: 显示邮箱、Credits/权益、退出、删除账户申请、客服邮箱。 | F20: 用户能看到购买权益和联系支持；敏感字段不暴露。 | G20: Creem审核要求；隐私合规 | H20: P1 | I20: 否 | J20: 未开始 | K20: =IF(J20="不适用","",IF(J20="已完成",1,IF(J20="待审核",0.9,IF(J20="进行中",0.5,IF(J20="已阻塞",0.25,0))))) -> 0 | L20: 登录会话/支付权益 | M20: 第5天 | N20: Codex | O20: =总览!$C$5+4 -> 46219
A21: DEV-017 | B21: 登录与账号 | C21: 数据删除 | D21: 实现账户数据删除/申请流程 | E21: 提供删除请求入口，按隐私政策删除或匿名化用户数据。 | F21: 删除流程可追踪；支付与安全日志按合法保留规则处理。 | G21: Privacy Policy；05部署§9-10 | H21: P1 | I21: 否 | J21: 未开始 | K21: =IF(J21="不适用","",IF(J21="已完成",1,IF(J21="待审核",0.9,IF(J21="进行中",0.5,IF(J21="已阻塞",0.25,0))))) -> 0 | L21: 账户页 | M21: 第6天 | N21: Codex+我 | O21: =总览!$C$5+5 -> 46220
A22: DEV-018 | B22: 登录与账号 | C22: 滥用防护 | D22: 登录频率限制与机器人防护 | E22: 对验证码发送、登录尝试、创建局等入口限流。 | F22: 异常频率返回429，不泄露账号是否存在。 | G22: 05部署§10 | H22: P1 | I22: 否 | J22: 已完成 | K22: =IF(J22="不适用","",IF(J22="已完成",1,IF(J22="待审核",0.9,IF(J22="进行中",0.5,IF(J22="已阻塞",0.25,0))))) -> 1 | L22: 登录页 | M22: 第6天 | N22: Codex | O22: =总览!$C$5+5 -> 46220 | Q22: 当前实现与测试环境已存在；关键 API 需要身份验证。 | R22: 保留生产环境的人工验证。 | S22: prisma/schema.prisma；apps/api/src/auth；apps/api/src/api-transport.ts
A23: DEV-019 | B23: 入口与房间 | C23: 首页 | D23: 英文首页部署与正式域名 | E23: 保持已上线首页可访问，首屏说明产品、玩法、价格和Beta状态。 | F23: 正式域名HTTPS稳定；所有CTA无死链。 | G23: 现有进度表；Creem审核 | H23: P0 | I23: 是 | J23: 已完成 | K23: =IF(J23="不适用","",IF(J23="已完成",1,IF(J23="待审核",0.9,IF(J23="进行中",0.5,IF(J23="已阻塞",0.25,0))))) -> 1 | M23: 第1天 | N23: 我 | O23: =总览!$C$5+0 -> 46215
A24: DEV-020 | B24: 入口与房间 | C24: 故事大厅 | D24: 实现故事局大厅 | E24: 调用 GET /api/v4/stories，展示《桑田诏》卡片、7天、历史权谋和可玩状态。 | F24: 首页/大厅能进入故事详情或角色选择，加载失败有重试。 | G24: 01基线§3；02状态机§9.1 | H24: P0 | I24: 是 | J24: 已完成 | K24: =IF(J24="不适用","",IF(J24="已完成",1,IF(J24="待审核",0.9,IF(J24="进行中",0.5,IF(J24="已阻塞",0.25,0))))) -> 1 | L24: stories API | M24: 第2天 | N24: Codex | O24: =总览!$C$5+1 -> 46216 | Q24: 目录、角色、创建、读取与持久化恢复均有当前实现和自动化验证。 | R24: 在 Vercel 正式域名上补做用户可见流程验收。 | S24: Railway test GET /api/v4/stories=200；apps/api 的 HTTP 全流程与重启持久化断言通过。
A25: DEV-021 | B25: 入口与房间 | C25: 故事详情 | D25: 实现故事详情与规则说明 | E25: 展示钩子、时长、角色、单人Beta说明、开始按钮。 | F25: 用户在30秒内理解目标、7天制和AI决策机制。 | G25: 07 PRD§4-5；09玩法§1-4 | H25: P1 | I25: 否 | J25: 已完成 | K25: =IF(J25="不适用","",IF(J25="已完成",1,IF(J25="待审核",0.9,IF(J25="进行中",0.5,IF(J25="已阻塞",0.25,0))))) -> 1 | L25: 故事大厅 | M25: 第2天 | N25: Codex | O25: =总览!$C$5+1 -> 46216 | Q25: 目录、角色、创建、读取与持久化恢复均有当前实现和自动化验证。 | R25: 在 Vercel 正式域名上补做用户可见流程验收。 | S25: Railway test GET /api/v4/stories=200；apps/api 的 HTTP 全流程与重启持久化断言通过。
A26: DEV-022 | B26: 入口与房间 | C26: 角色选择 | D26: 实现角色选择页 | E26: GET roles；MVP 仅浙江总督可选，其他角色显示AI控制。 | F26: 只能以 zhejiang_governor 正式创建StoryRun。 | G26: 01基线§2；02状态机§9.3-9.4 | H26: P0 | I26: 是 | J26: 已完成 | K26: =IF(J26="不适用","",IF(J26="已完成",1,IF(J26="待审核",0.9,IF(J26="进行中",0.5,IF(J26="已阻塞",0.25,0))))) -> 1 | L26: stories/roles API | M26: 第2天 | N26: Codex | O26: =总览!$C$5+1 -> 46216 | Q26: 目录、角色、创建、读取与持久化恢复均有当前实现和自动化验证。 | R26: 在 Vercel 正式域名上补做用户可见流程验收。 | S26: Railway test GET /api/v4/stories=200；apps/api 的 HTTP 全流程与重启持久化断言通过。
A27: DEV-023 | B27: 入口与房间 | C27: 开启房间 | D27: 创建故事局/开启房间 | E27: 点击开始调用 POST /api/v4/story-runs，使用幂等键，成功后进入 /game?runId=...。 | F27: 创建一次只产生一个StoryRun；初始day=1、version=1、awaiting_decision。 | G27: 02状态机§9.4；用户新增要求 | H27: P0 | I27: 是 | J27: 已完成 | K27: =IF(J27="不适用","",IF(J27="已完成",1,IF(J27="待审核",0.9,IF(J27="进行中",0.5,IF(J27="已阻塞",0.25,0))))) -> 1 | L27: 登录/角色选择/数据库 | M27: 第2天 | N27: Codex | O27: =总览!$C$5+1 -> 46216 | Q27: 目录、角色、创建、读取与持久化恢复均有当前实现和自动化验证。 | R27: 在 Vercel 正式域名上补做用户可见流程验收。 | S27: Railway test GET /api/v4/stories=200；apps/api 的 HTTP 全流程与重启持久化断言通过。
A28: DEV-024 | B28: 入口与房间 | C28: 进入房间 | D28: 输入 runId 或继续上次故事局 | E28: 提供“继续游戏/输入房间ID”入口，GET run 后进入唯一游戏页。 | F28: 合法runId恢复原状态；无效runId明确提示，不静默创建新局。 | G28: 02状态机§7、9.5；用户新增要求 | H28: P0 | I28: 是 | J28: 已完成 | K28: =IF(J28="不适用","",IF(J28="已完成",1,IF(J28="待审核",0.9,IF(J28="进行中",0.5,IF(J28="已阻塞",0.25,0))))) -> 1 | L28: GET StoryRun | M28: 第2天 | N28: Codex | O28: =总览!$C$5+1 -> 46216 | Q28: 目录、角色、创建、读取与持久化恢复均有当前实现和自动化验证。 | R28: 在 Vercel 正式域名上补做用户可见流程验收。 | S28: Railway test GET /api/v4/stories=200；apps/api 的 HTTP 全流程与重启持久化断言通过。
A29: DEV-025 | B29: 入口与房间 | C29: 房间恢复 | D29: 刷新与跨设备恢复 | E29: 浏览器只保存runId和草稿；权威状态从服务端恢复。 | F29: awaiting_decision/resolving/day_advance/finalization/finished 均恢复正确。 | G29: 01基线§4；02状态机§7 | H29: P0 | I29: 是 | J29: 已完成 | K29: =IF(J29="不适用","",IF(J29="已完成",1,IF(J29="待审核",0.9,IF(J29="进行中",0.5,IF(J29="已阻塞",0.25,0))))) -> 1 | L29: 进入房间/状态机 | M29: 第3天 | N29: Codex | O29: =总览!$C$5+2 -> 46217 | Q29: 目录、角色、创建、读取与持久化恢复均有当前实现和自动化验证。 | R29: 在 Vercel 正式域名上补做用户可见流程验收。 | S29: Railway test GET /api/v4/stories=200；apps/api 的 HTTP 全流程与重启持久化断言通过。
A30: DEV-026 | B30: 入口与房间 | C30: 继续/重开 | D30: 完成局后重开新局 | E30: 结局页提供Replay，创建新runId，旧局保持只读。 | F30: 重开不覆盖旧局；用户可在我的游戏查看两局。 | G30: 04验收F-012；02状态机§2 | H30: P1 | I30: 否 | J30: 未开始 | K30: =IF(J30="不适用","",IF(J30="已完成",1,IF(J30="待审核",0.9,IF(J30="进行中",0.5,IF(J30="已阻塞",0.25,0))))) -> 0 | L30: 最终裁决 | M30: 第5天 | N30: Codex | O30: =总览!$C$5+4 -> 46219
A31: DEV-027 | B31: 入口与房间 | C31: 多人边界 | D31: 明确真人加入房间不进入当前MVP | E31: UI文案避免让用户误以为当前支持多人实时；保留未来入口但禁用。 | F31: 正式Beta不出现无法使用的“邀请真人加入”按钮。 | G31: 01基线§2；07 PRD§10 | H31: P0 | I31: 是 | J31: 不适用 | K31: =IF(J31="不适用","",IF(J31="已完成",1,IF(J31="待审核",0.9,IF(J31="进行中",0.5,IF(J31="已阻塞",0.25,0))))) | L31: 范围锁定 | M31: 第2天 | N31: 我+Codex | O31: =总览!$C$5+1 -> 46216 | Q31: 原表限定单人MVP/禁止真人多人；现行代码已演进为房间与多用户实现，原验收口径不再适用。 | R31: 后续以 v1.4 房间/多用户范围重建对应任务与验收口径。 | S31: apps/api/src/rooms.controller.ts；docs/auto-execute/many-worlds-v14-p0-closeout-final-acceptance-gate.md
A32: DEV-028 | B32: 数据库与运行态 | C32: 迁移 | D32: 建立 StoryRun 表 | E32: 保存userId、templateKey、mode、status、day、selectedRoleKey、stateJson、version、时间字段。 | F32: 迁移可重复执行；关键字段和索引符合文档。 | G32: 08数据库§6 | H32: P0 | I32: 是 | J32: 已完成 | K32: =IF(J32="不适用","",IF(J32="已完成",1,IF(J32="待审核",0.9,IF(J32="进行中",0.5,IF(J32="已阻塞",0.25,0))))) -> 1 | L32: Supabase项目 | M32: 第2天 | N32: Codex | O32: =总览!$C$5+1 -> 46216 | Q32: Prisma 持久化、事件、AI任务、版本与幂等控制均在当前代码和测试内。 | R32: 生产数据与权限策略继续按发布环境复核。 | S32: prisma/schema.prisma；apps/api/src/prisma-mvp-storage.ts；apps/api/src/story.service.spec.ts
A33: DEV-029 | B33: 数据库与运行态 | C33: 迁移 | D33: 建立 StoryEvent 表 | E33: 追加式保存故事、prompt、decision、result、change、maneuver、critical、day_end、final等。 | F33: 事件按run/day/time可查询；事件不可被普通业务覆盖修改。 | G33: 08数据库§7 | H33: P0 | I33: 是 | J33: 已完成 | K33: =IF(J33="不适用","",IF(J33="已完成",1,IF(J33="待审核",0.9,IF(J33="进行中",0.5,IF(J33="已阻塞",0.25,0))))) -> 1 | L33: StoryRun表 | M33: 第2天 | N33: Codex | O33: =总览!$C$5+1 -> 46216 | Q33: Prisma 持久化、事件、AI任务、版本与幂等控制均在当前代码和测试内。 | R33: 生产数据与权限策略继续按发布环境复核。 | S33: prisma/schema.prisma；apps/api/src/prisma-mvp-storage.ts；apps/api/src/story.service.spec.ts
A34: DEV-030 | B34: 数据库与运行态 | C34: AI账本 | D34: 建立 AiTask 表 | E34: 真实模型接入时记录任务状态、输入摘要、输出、校验错误、重试、token、成本、耗时。 | F34: 每次主要AI调用可追踪；普通日志不保存敏感全文。 | G34: 08数据库§9；05部署§7 | H34: P0 | I34: 是 | J34: 已完成 | K34: =IF(J34="不适用","",IF(J34="已完成",1,IF(J34="待审核",0.9,IF(J34="进行中",0.5,IF(J34="已阻塞",0.25,0))))) -> 1 | L34: StoryRun/StoryEvent | M34: 第3天 | N34: Codex | O34: =总览!$C$5+2 -> 46217 | Q34: Prisma 持久化、事件、AI任务、版本与幂等控制均在当前代码和测试内。 | R34: 生产数据与权限策略继续按发布环境复核。 | S34: prisma/schema.prisma；apps/api/src/prisma-mvp-storage.ts；apps/api/src/story.service.spec.ts
A35: DEV-031 | B35: 数据库与运行态 | C35: 初始化 | D35: StoryRun 初始状态生成 | E35: 从剧本配置生成世界变量、角色变量、关系、谋划次数、activePrompt和开场事件。 | F35: 创建事务完成后直接进入awaiting_decision；失败不留下半成品run。 | G35: 02状态机§2.1；08数据库§12.1 | H35: P0 | I35: 是 | J35: 已完成 | K35: =IF(J35="不适用","",IF(J35="已完成",1,IF(J35="待审核",0.9,IF(J35="进行中",0.5,IF(J35="已阻塞",0.25,0))))) -> 1 | L35: 配置校验/数据库 | M35: 第2天 | N35: Codex | O35: =总览!$C$5+1 -> 46216 | Q35: Prisma 持久化、事件、AI任务、版本与幂等控制均在当前代码和测试内。 | R35: 生产数据与权限策略继续按发布环境复核。 | S35: prisma/schema.prisma；apps/api/src/prisma-mvp-storage.ts；apps/api/src/story.service.spec.ts
A36: DEV-032 | B36: 数据库与运行态 | C36: 公共投影 | D36: StoryEvent → NarrativeEntry 公共投影 | E36: 过滤hidden事件，将story/result/day_end投影为story，将可见patch投影为change_summary。 | F36: 公共响应不含internalGain/internalRisk/statePatch预测/privateReasoning。 | G36: 08数据库§8；02状态机§8-9.6 | H36: P0 | I36: 是 | J36: 已完成 | K36: =IF(J36="不适用","",IF(J36="已完成",1,IF(J36="待审核",0.9,IF(J36="进行中",0.5,IF(J36="已阻塞",0.25,0))))) -> 1 | L36: StoryEvent表/共享类型 | M36: 第3天 | N36: Codex | O36: =总览!$C$5+2 -> 46217 | Q36: Prisma 持久化、事件、AI任务、版本与幂等控制均在当前代码和测试内。 | R36: 生产数据与权限策略继续按发布环境复核。 | S36: prisma/schema.prisma；apps/api/src/prisma-mvp-storage.ts；apps/api/src/story.service.spec.ts
A37: DEV-033 | B37: 数据库与运行态 | C37: 乐观锁 | D37: 实现 version 并发控制 | E37: 每次权威写入校验version并+1；旧版本返回VERSION_CONFLICT。 | F37: 双标签页并发时只有一个请求成功，状态无覆盖。 | G37: 02状态机§5.1 | H37: P0 | I37: 是 | J37: 已完成 | K37: =IF(J37="不适用","",IF(J37="已完成",1,IF(J37="待审核",0.9,IF(J37="进行中",0.5,IF(J37="已阻塞",0.25,0))))) -> 1 | L37: StoryRun表 | M37: 第3天 | N37: Codex | O37: =总览!$C$5+2 -> 46217 | Q37: Prisma 持久化、事件、AI任务、版本与幂等控制均在当前代码和测试内。 | R37: 生产数据与权限策略继续按发布环境复核。 | S37: prisma/schema.prisma；apps/api/src/prisma-mvp-storage.ts；apps/api/src/story.service.spec.ts
A38: DEV-034 | B38: 数据库与运行态 | C38: 幂等 | D38: 实现 Idempotency-Key 账本 | E38: runId+endpoint+key唯一；相同请求返回同一结果，不同请求体复用key被拒绝。 | F38: 重复点击/网络重试不会重复扣次数、重复写事件或重复支付权益。 | G38: 02状态机§5.2 | H38: P0 | I38: 是 | J38: 已完成 | K38: =IF(J38="不适用","",IF(J38="已完成",1,IF(J38="待审核",0.9,IF(J38="进行中",0.5,IF(J38="已阻塞",0.25,0))))) -> 1 | L38: 数据库事务 | M38: 第3天 | N38: Codex | O38: =总览!$C$5+2 -> 46217 | Q38: Prisma 持久化、事件、AI任务、版本与幂等控制均在当前代码和测试内。 | R38: 生产数据与权限策略继续按发布环境复核。 | S38: prisma/schema.prisma；apps/api/src/prisma-mvp-storage.ts；apps/api/src/story.service.spec.ts
A39: DEV-035 | B39: 数据库与运行态 | C39: 事务 | D39: 决策与谋划原子事务 | E39: 状态更新、事件追加、计数、筹码和version必须全成或全败。 | F39: 注入任一步骤失败后状态与事件均不出现半落账。 | G39: 08数据库§15 | H39: P0 | I39: 是 | J39: 已完成 | K39: =IF(J39="不适用","",IF(J39="已完成",1,IF(J39="待审核",0.9,IF(J39="进行中",0.5,IF(J39="已阻塞",0.25,0))))) -> 1 | L39: 乐观锁/幂等 | M39: 第3天 | N39: Codex | O39: =总览!$C$5+2 -> 46217 | Q39: Prisma 持久化、事件、AI任务、版本与幂等控制均在当前代码和测试内。 | R39: 生产数据与权限策略继续按发布环境复核。 | S39: prisma/schema.prisma；apps/api/src/prisma-mvp-storage.ts；apps/api/src/story.service.spec.ts
A40: DEV-036 | B40: 数据库与运行态 | C40: 权限 | D40: 用户级数据隔离 | E40: API按userId校验StoryRun所有权；service role仅服务端。 | F40: 修改runId不能读取或修改他人的游戏数据。 | G40: Supabase RLS；05部署§10 | H40: P0 | I40: 是 | J40: 已完成 | K40: =IF(J40="不适用","",IF(J40="已完成",1,IF(J40="待审核",0.9,IF(J40="进行中",0.5,IF(J40="已阻塞",0.25,0))))) -> 1 | L40: 登录/StoryRun | M40: 第4天 | N40: Codex | O40: =总览!$C$5+3 -> 46218 | Q40: Prisma 持久化、事件、AI任务、版本与幂等控制均在当前代码和测试内。 | R40: 生产数据与权限策略继续按发布环境复核。 | S40: prisma/schema.prisma；apps/api/src/prisma-mvp-storage.ts；apps/api/src/story.service.spec.ts
A41: DEV-037 | B41: 数据库与运行态 | C41: 备份恢复 | D41: 数据库备份与恢复策略 | E41: staging/prod独立；配置每日备份，MVP恢复目标RPO≤15分钟、RTO≤2小时。 | F41: 至少完成一次从备份恢复到测试项目的演练并记录结果。 | G41: 05部署§12-13 | H41: P1 | I41: 是 | J41: 进行中 | K41: =IF(J41="不适用","",IF(J41="已完成",1,IF(J41="待审核",0.9,IF(J41="进行中",0.5,IF(J41="已阻塞",0.25,0))))) -> 0.5 | L41: 生产数据库 | M41: 第6天 | N41: 我+Codex | O41: =总览!$C$5+5 -> 46220 | Q41: 本地备份/恢复脚本与历史证据存在；当前 Railway/Supabase 生产备份策略未完成验证。 | R41: 完成生产恢复演练与备份保留策略确认。 | S41: scripts/ops；docs/auto-execute/results/db-restore-smoke-*.json
A42: DEV-038 | B42: 后端API | C42: 剧本列表 | D42: GET /api/v4/stories | E42: 按统一响应和错误码实现控制器、DTO、Service与权限校验。 | F42: 返回可玩剧本列表，MVP至少含sangtian。 | G42: 02状态机§9.1 | H42: P0 | I42: 是 | J42: 已完成 | K42: =IF(J42="不适用","",IF(J42="已完成",1,IF(J42="待审核",0.9,IF(J42="进行中",0.5,IF(J42="已阻塞",0.25,0))))) -> 1 | L42: 数据库/状态机 | M42: 第3天 | N42: Codex | O42: =总览!$C$5+2 -> 46217 | Q42: 对应 v4 API、健康检查与错误处理已在当前 Nest 服务中实现；API 测试通过。 | R42: 将公开 API 的端到端浏览器验收纳入 Vercel 发布后检查。 | S42: apps/api/src/*.controller.ts；pnpm test:api；Railway test /api/health、/api/health/ready=200。
A43: DEV-039 | B43: 后端API | C43: 剧本详情 | D43: GET /api/v4/stories/:templateKey | E43: 按统一响应和错误码实现控制器、DTO、Service与权限校验。 | F43: 返回公开剧本信息，不返回隐藏角色目标和后台规则。 | G43: 02状态机§9.2 | H43: P0 | I43: 是 | J43: 已完成 | K43: =IF(J43="不适用","",IF(J43="已完成",1,IF(J43="待审核",0.9,IF(J43="进行中",0.5,IF(J43="已阻塞",0.25,0))))) -> 1 | L43: 数据库/状态机 | M43: 第3天 | N43: Codex | O43: =总览!$C$5+2 -> 46217 | Q43: 对应 v4 API、健康检查与错误处理已在当前 Nest 服务中实现；API 测试通过。 | R43: 将公开 API 的端到端浏览器验收纳入 Vercel 发布后检查。 | S43: apps/api/src/*.controller.ts；pnpm test:api；Railway test /api/health、/api/health/ready=200。
A44: DEV-040 | B44: 后端API | C44: 角色列表 | D44: GET /api/v4/stories/:templateKey/roles | E44: 按统一响应和错误码实现控制器、DTO、Service与权限校验。 | F44: 返回角色和playable状态。 | G44: 02状态机§9.3 | H44: P0 | I44: 是 | J44: 已完成 | K44: =IF(J44="不适用","",IF(J44="已完成",1,IF(J44="待审核",0.9,IF(J44="进行中",0.5,IF(J44="已阻塞",0.25,0))))) -> 1 | L44: 数据库/状态机 | M44: 第3天 | N44: Codex | O44: =总览!$C$5+2 -> 46217 | Q44: 对应 v4 API、健康检查与错误处理已在当前 Nest 服务中实现；API 测试通过。 | R44: 将公开 API 的端到端浏览器验收纳入 Vercel 发布后检查。 | S44: apps/api/src/*.controller.ts；pnpm test:api；Railway test /api/health、/api/health/ready=200。
A45: DEV-041 | B45: 后端API | C45: 创建局 | D45: POST /api/v4/story-runs | E45: 按统一响应和错误码实现控制器、DTO、Service与权限校验。 | F45: 创建开场和activePrompt，返回完整公共视图。 | G45: 02状态机§9.4 | H45: P0 | I45: 是 | J45: 已完成 | K45: =IF(J45="不适用","",IF(J45="已完成",1,IF(J45="待审核",0.9,IF(J45="进行中",0.5,IF(J45="已阻塞",0.25,0))))) -> 1 | L45: 数据库/状态机 | M45: 第3天 | N45: Codex | O45: =总览!$C$5+2 -> 46217 | Q45: 对应 v4 API、健康检查与错误处理已在当前 Nest 服务中实现；API 测试通过。 | R45: 将公开 API 的端到端浏览器验收纳入 Vercel 发布后检查。 | S45: apps/api/src/*.controller.ts；pnpm test:api；Railway test /api/health、/api/health/ready=200。
A46: DEV-042 | B46: 后端API | C46: 获取局 | D46: GET /api/v4/story-runs/:runId | E46: 按统一响应和错误码实现控制器、DTO、Service与权限校验。 | F46: 恢复run、timeline、activePrompt、criticalEvent、maneuverPanel。 | G46: 02状态机§9.5 | H46: P0 | I46: 是 | J46: 已完成 | K46: =IF(J46="不适用","",IF(J46="已完成",1,IF(J46="待审核",0.9,IF(J46="进行中",0.5,IF(J46="已阻塞",0.25,0))))) -> 1 | L46: 数据库/状态机 | M46: 第3天 | N46: Codex | O46: =总览!$C$5+2 -> 46217 | Q46: 对应 v4 API、健康检查与错误处理已在当前 Nest 服务中实现；API 测试通过。 | R46: 将公开 API 的端到端浏览器验收纳入 Vercel 发布后检查。 | S46: apps/api/src/*.controller.ts；pnpm test:api；Railway test /api/health、/api/health/ready=200。
A47: DEV-043 | B47: 后端API | C47: 叙事增量 | D47: GET /api/v4/story-runs/:runId/messages | E47: 按统一响应和错误码实现控制器、DTO、Service与权限校验。 | F47: 支持after/limit，按时间返回NarrativeEntry。 | G47: 02状态机§9.6 | H47: P0 | I47: 是 | J47: 已完成 | K47: =IF(J47="不适用","",IF(J47="已完成",1,IF(J47="待审核",0.9,IF(J47="进行中",0.5,IF(J47="已阻塞",0.25,0))))) -> 1 | L47: 数据库/状态机 | M47: 第3天 | N47: Codex | O47: =总览!$C$5+2 -> 46217 | Q47: 对应 v4 API、健康检查与错误处理已在当前 Nest 服务中实现；API 测试通过。 | R47: 将公开 API 的端到端浏览器验收纳入 Vercel 发布后检查。 | S47: apps/api/src/*.controller.ts；pnpm test:api；Railway test /api/health、/api/health/ready=200。
A48: DEV-044 | B48: 后端API | C48: Dashboard | D48: GET /api/v4/story-runs/:runId/dashboard | E48: 按统一响应和错误码实现控制器、DTO、Service与权限校验。 | F48: 返回玩家可见世界、角色、关系、风险、线索和谋划面板。 | G48: 02状态机§9.7 | H48: P0 | I48: 是 | J48: 已完成 | K48: =IF(J48="不适用","",IF(J48="已完成",1,IF(J48="待审核",0.9,IF(J48="进行中",0.5,IF(J48="已阻塞",0.25,0))))) -> 1 | L48: 数据库/状态机 | M48: 第3天 | N48: Codex | O48: =总览!$C$5+2 -> 46217 | Q48: 对应 v4 API、健康检查与错误处理已在当前 Nest 服务中实现；API 测试通过。 | R48: 将公开 API 的端到端浏览器验收纳入 Vercel 发布后检查。 | S48: apps/api/src/*.controller.ts；pnpm test:api；Railway test /api/health、/api/health/ready=200。
A49: DEV-045 | B49: 后端API | C49: 提交决策 | D49: POST .../messages/:eventId/decisions | E49: 按统一响应和错误码实现控制器、DTO、Service与权限校验。 | F49: 支持main_decision/critical_response，1-200字，ActionGuard与幂等。 | G49: 02状态机§9.8 | H49: P0 | I49: 是 | J49: 已完成 | K49: =IF(J49="不适用","",IF(J49="已完成",1,IF(J49="待审核",0.9,IF(J49="进行中",0.5,IF(J49="已阻塞",0.25,0))))) -> 1 | L49: 数据库/状态机 | M49: 第3天 | N49: Codex | O49: =总览!$C$5+2 -> 46217 | Q49: 对应 v4 API、健康检查与错误处理已在当前 Nest 服务中实现；API 测试通过。 | R49: 将公开 API 的端到端浏览器验收纳入 Vercel 发布后检查。 | S49: apps/api/src/*.controller.ts；pnpm test:api；Railway test /api/health、/api/health/ready=200。
A50: DEV-046 | B50: 后端API | C50: 延后事件 | D50: POST .../messages/:eventId/defer | E50: 按统一响应和错误码实现控制器、DTO、Service与权限校验。 | F50: 追加deferred事件，刷新可恢复，不完成决策。 | G50: 02状态机§9.9 | H50: P0 | I50: 是 | J50: 已完成 | K50: =IF(J50="不适用","",IF(J50="已完成",1,IF(J50="待审核",0.9,IF(J50="进行中",0.5,IF(J50="已阻塞",0.25,0))))) -> 1 | L50: 数据库/状态机 | M50: 第3天 | N50: Codex | O50: =总览!$C$5+2 -> 46217 | Q50: 对应 v4 API、健康检查与错误处理已在当前 Nest 服务中实现；API 测试通过。 | R50: 将公开 API 的端到端浏览器验收纳入 Vercel 发布后检查。 | S50: apps/api/src/*.controller.ts；pnpm test:api；Railway test /api/health、/api/health/ready=200。
A51: DEV-047 | B51: 后端API | C51: 提交谋划 | D51: POST .../maneuvers | E51: 按统一响应和错误码实现控制器、DTO、Service与权限校验。 | F51: 支持contact/investigate/leverage/custom，成功扣1次。 | G51: 02状态机§9.10 | H51: P0 | I51: 是 | J51: 已完成 | K51: =IF(J51="不适用","",IF(J51="已完成",1,IF(J51="待审核",0.9,IF(J51="进行中",0.5,IF(J51="已阻塞",0.25,0))))) -> 1 | L51: 数据库/状态机 | M51: 第3天 | N51: Codex | O51: =总览!$C$5+2 -> 46217 | Q51: 对应 v4 API、健康检查与错误处理已在当前 Nest 服务中实现；API 测试通过。 | R51: 将公开 API 的端到端浏览器验收纳入 Vercel 发布后检查。 | S51: apps/api/src/*.controller.ts；pnpm test:api；Railway test /api/health、/api/health/ready=200。
A52: DEV-048 | B52: 后端API | C52: 推进天数 | D52: POST .../advance-day | E52: 按统一响应和错误码实现控制器、DTO、Service与权限校验。 | F52: 当天2次决策完成后推进，谋划不阻塞、不结转。 | G52: 02状态机§9.11 | H52: P0 | I52: 是 | J52: 已完成 | K52: =IF(J52="不适用","",IF(J52="已完成",1,IF(J52="待审核",0.9,IF(J52="进行中",0.5,IF(J52="已阻塞",0.25,0))))) -> 1 | L52: 数据库/状态机 | M52: 第3天 | N52: Codex | O52: =总览!$C$5+2 -> 46217 | Q52: 对应 v4 API、健康检查与错误处理已在当前 Nest 服务中实现；API 测试通过。 | R52: 将公开 API 的端到端浏览器验收纳入 Vercel 发布后检查。 | S52: apps/api/src/*.controller.ts；pnpm test:api；Railway test /api/health、/api/health/ready=200。
A53: DEV-049 | B53: 后端API | C53: 最终裁决 | D53: POST .../finalize | E53: 按统一响应和错误码实现控制器、DTO、Service与权限校验。 | F53: 仅day7且12次决策完成可执行，幂等返回同一结局。 | G53: 02状态机§9.12 | H53: P0 | I53: 是 | J53: 已完成 | K53: =IF(J53="不适用","",IF(J53="已完成",1,IF(J53="待审核",0.9,IF(J53="进行中",0.5,IF(J53="已阻塞",0.25,0))))) -> 1 | L53: 数据库/状态机 | M53: 第3天 | N53: Codex | O53: =总览!$C$5+2 -> 46217 | Q53: 对应 v4 API、健康检查与错误处理已在当前 Nest 服务中实现；API 测试通过。 | R53: 将公开 API 的端到端浏览器验收纳入 Vercel 发布后检查。 | S53: apps/api/src/*.controller.ts；pnpm test:api；Railway test /api/health、/api/health/ready=200。
A54: DEV-050 | B54: 后端API | C54: 健康检查 | D54: 实现 /health 和依赖检查 | E54: 检查API进程、数据库连接和必要配置，不泄露密钥。 | F54: 部署平台可用health check判断服务是否健康。 | G54: 05部署§14 | H54: P0 | I54: 是 | J54: 已完成 | K54: =IF(J54="不适用","",IF(J54="已完成",1,IF(J54="待审核",0.9,IF(J54="进行中",0.5,IF(J54="已阻塞",0.25,0))))) -> 1 | L54: 后端部署 | M54: 第4天 | N54: Codex | O54: =总览!$C$5+3 -> 46218 | Q54: 对应 v4 API、健康检查与错误处理已在当前 Nest 服务中实现；API 测试通过。 | R54: 将公开 API 的端到端浏览器验收纳入 Vercel 发布后检查。 | S54: apps/api/src/*.controller.ts；pnpm test:api；Railway test /api/health、/api/health/ready=200。
A55: DEV-051 | B55: 后端API | C55: 错误契约 | D55: 统一HTTP状态码与错误码 | E55: 实现400/404/409/422/429/502/503等契约，前端按code显示可恢复提示。 | F55: 自动化测试覆盖关键错误码，无裸堆栈返回前端。 | G55: 02状态机§10 | H55: P0 | I55: 是 | J55: 已完成 | K55: =IF(J55="不适用","",IF(J55="已完成",1,IF(J55="待审核",0.9,IF(J55="进行中",0.5,IF(J55="已阻塞",0.25,0))))) -> 1 | L55: API接口 | M55: 第4天 | N55: Codex | O55: =总览!$C$5+3 -> 46218 | Q55: 对应 v4 API、健康检查与错误处理已在当前 Nest 服务中实现；API 测试通过。 | R55: 将公开 API 的端到端浏览器验收纳入 Vercel 发布后检查。 | S55: apps/api/src/*.controller.ts；pnpm test:api；Railway test /api/health、/api/health/ready=200。
A56: DEV-052 | B56: 主游戏UI | C56: 唯一游戏路由 | D56: /game?runId=<runId> | E56: 按现有古典三栏设计接入真实公共投影和状态机，保持顶部/左右栏稳定。 | F56: 8种状态全部在单一路由内渲染。 | G56: 01基线§5；11 UI§2 | H56: P0 | I56: 是 | J56: 待审核 | K56: =IF(J56="不适用","",IF(J56="已完成",1,IF(J56="待审核",0.9,IF(J56="进行中",0.5,IF(J56="已阻塞",0.25,0))))) -> 0.9 | L56: GET run/API公共投影 | M56: 第3天 | N56: Codex | O56: =总览!$C$5+2 -> 46217 | Q56: 页面与组件实现、现有截图和前端语法校验均存在；最终 P0 视觉验收仍未全部完成。 | R56: 在 Vercel 预览/正式域名执行全页面视觉与交互验收。 | S56: apps/web/public；docs/auto-execute/screenshots/current-UI*.png；pnpm --filter @apps/web typecheck 通过。
A57: DEV-053 | B57: 主游戏UI | C57: 固定顶部 | D57: TopGameBar | E57: 按现有古典三栏设计接入真实公共投影和状态机，保持顶部/左右栏稳定。 | F57: 地点、日期、裁决倒计时、决策/谋划次数和世界状态固定。 | G57: 11 UI§3.1 | H57: P0 | I57: 是 | J57: 待审核 | K57: =IF(J57="不适用","",IF(J57="已完成",1,IF(J57="待审核",0.9,IF(J57="进行中",0.5,IF(J57="已阻塞",0.25,0))))) -> 0.9 | L57: GET run/API公共投影 | M57: 第3天 | N57: Codex | O57: =总览!$C$5+2 -> 46217 | Q57: 页面与组件实现、现有截图和前端语法校验均存在；最终 P0 视觉验收仍未全部完成。 | R57: 在 Vercel 预览/正式域名执行全页面视觉与交互验收。 | S57: apps/web/public；docs/auto-execute/screenshots/current-UI*.png；pnpm --filter @apps/web typecheck 通过。
A58: DEV-054 | B58: 主游戏UI | C58: 左侧身份栏 | D58: LeftPlayerPanel | E58: 按现有古典三栏设计接入真实公共投影和状态机，保持顶部/左右栏稳定。 | F58: 身份、命运问题、目标、资源、筹码和风险固定。 | G58: 11 UI§3.2 | H58: P0 | I58: 是 | J58: 待审核 | K58: =IF(J58="不适用","",IF(J58="已完成",1,IF(J58="待审核",0.9,IF(J58="进行中",0.5,IF(J58="已阻塞",0.25,0))))) -> 0.9 | L58: GET run/API公共投影 | M58: 第3天 | N58: Codex | O58: =总览!$C$5+2 -> 46217 | Q58: 页面与组件实现、现有截图和前端语法校验均存在；最终 P0 视觉验收仍未全部完成。 | R58: 在 Vercel 预览/正式域名执行全页面视觉与交互验收。 | S58: apps/web/public；docs/auto-execute/screenshots/current-UI*.png；pnpm --filter @apps/web typecheck 通过。
A59: DEV-055 | B59: 主游戏UI | C59: 右侧谋划栏 | D59: RightManeuverPanel | E59: 按现有古典三栏设计接入真实公共投影和状态机，保持顶部/左右栏稳定。 | F59: 谋划次数、人物、推进目标、筹码、自拟谋划、进入下一天。 | G59: 11 UI§3.3 | H59: P0 | I59: 是 | J59: 待审核 | K59: =IF(J59="不适用","",IF(J59="已完成",1,IF(J59="待审核",0.9,IF(J59="进行中",0.5,IF(J59="已阻塞",0.25,0))))) -> 0.9 | L59: GET run/API公共投影 | M59: 第3天 | N59: Codex | O59: =总览!$C$5+2 -> 46217 | Q59: 页面与组件实现、现有截图和前端语法校验均存在；最终 P0 视觉验收仍未全部完成。 | R59: 在 Vercel 预览/正式域名执行全页面视觉与交互验收。 | S59: apps/web/public；docs/auto-execute/screenshots/current-UI*.png；pnpm --filter @apps/web typecheck 通过。
A60: DEV-056 | B60: 主游戏UI | C60: 持续叙事时间线 | D60: NarrativeTimeline | E60: 按现有古典三栏设计接入真实公共投影和状态机，保持顶部/左右栏稳定。 | F60: 故事、决策、推演、结果、变化按时间连续追加，不分页。 | G60: 07 PRD§6；11 UI§4 | H60: P0 | I60: 是 | J60: 待审核 | K60: =IF(J60="不适用","",IF(J60="已完成",1,IF(J60="待审核",0.9,IF(J60="进行中",0.5,IF(J60="已阻塞",0.25,0))))) -> 0.9 | L60: GET run/API公共投影 | M60: 第3天 | N60: Codex | O60: =总览!$C$5+2 -> 46217 | Q60: 页面与组件实现、现有截图和前端语法校验均存在；最终 P0 视觉验收仍未全部完成。 | R60: 在 Vercel 预览/正式域名执行全页面视觉与交互验收。 | S60: apps/web/public；docs/auto-execute/screenshots/current-UI*.png；pnpm --filter @apps/web typecheck 通过。
A61: DEV-057 | B61: 主游戏UI | C61: UI01 开场 | D61: StoryBlock | E61: 按现有古典三栏设计接入真实公共投影和状态机，保持顶部/左右栏稳定。 | F61: 日期、地点、章节与故事正文，无流程按钮。 | G61: 11 UI§6 | H61: P0 | I61: 是 | J61: 待审核 | K61: =IF(J61="不适用","",IF(J61="已完成",1,IF(J61="待审核",0.9,IF(J61="进行中",0.5,IF(J61="已阻塞",0.25,0))))) -> 0.9 | L61: GET run/API公共投影 | M61: 第3天 | N61: Codex | O61: =总览!$C$5+2 -> 46217 | Q61: 页面与组件实现、现有截图和前端语法校验均存在；最终 P0 视觉验收仍未全部完成。 | R61: 在 Vercel 预览/正式域名执行全页面视觉与交互验收。 | S61: apps/web/public；docs/auto-execute/screenshots/current-UI*.png；pnpm --filter @apps/web typecheck 通过。
A62: DEV-058 | B62: 主游戏UI | C62: UI02 主线决策 | D62: DecisionComposer | E62: 按现有古典三栏设计接入真实公共投影和状态机，保持顶部/左右栏稳定。 | F62: A/B/C标题、统一输入框和提交决策。 | G62: 11 UI§7 | H62: P0 | I62: 是 | J62: 待审核 | K62: =IF(J62="不适用","",IF(J62="已完成",1,IF(J62="待审核",0.9,IF(J62="进行中",0.5,IF(J62="已阻塞",0.25,0))))) -> 0.9 | L62: GET run/API公共投影 | M62: 第3天 | N62: Codex | O62: =总览!$C$5+2 -> 46217 | Q62: 页面与组件实现、现有截图和前端语法校验均存在；最终 P0 视觉验收仍未全部完成。 | R62: 在 Vercel 预览/正式域名执行全页面视觉与交互验收。 | S62: apps/web/public；docs/auto-execute/screenshots/current-UI*.png；pnpm --filter @apps/web typecheck 通过。
A63: DEV-059 | B63: 主游戏UI | C63: UI03 推演中 | D63: SimulationBlock | E63: 按现有古典三栏设计接入真实公共投影和状态机，保持顶部/左右栏稳定。 | F63: 只显示玩家决定和“AI 正在推演局势……”。 | G63: 11 UI§8 | H63: P0 | I63: 是 | J63: 待审核 | K63: =IF(J63="不适用","",IF(J63="已完成",1,IF(J63="待审核",0.9,IF(J63="进行中",0.5,IF(J63="已阻塞",0.25,0))))) -> 0.9 | L63: GET run/API公共投影 | M63: 第3天 | N63: Codex | O63: =总览!$C$5+2 -> 46217 | Q63: 页面与组件实现、现有截图和前端语法校验均存在；最终 P0 视觉验收仍未全部完成。 | R63: 在 Vercel 预览/正式域名执行全页面视觉与交互验收。 | S63: apps/web/public；docs/auto-execute/screenshots/current-UI*.png；pnpm --filter @apps/web typecheck 通过。
A64: DEV-060 | B64: 主游戏UI | C64: UI04 结果与变化 | D64: Result + ChangeSummary | E64: 按现有古典三栏设计接入真实公共投影和状态机，保持顶部/左右栏稳定。 | F64: 先结果故事，再本次变化，必要时继续出现下一prompt。 | G64: 11 UI§9 | H64: P0 | I64: 是 | J64: 待审核 | K64: =IF(J64="不适用","",IF(J64="已完成",1,IF(J64="待审核",0.9,IF(J64="进行中",0.5,IF(J64="已阻塞",0.25,0))))) -> 0.9 | L64: GET run/API公共投影 | M64: 第3天 | N64: Codex | O64: =总览!$C$5+2 -> 46217 | Q64: 页面与组件实现、现有截图和前端语法校验均存在；最终 P0 视觉验收仍未全部完成。 | R64: 在 Vercel 预览/正式域名执行全页面视觉与交互验收。 | S64: apps/web/public；docs/auto-execute/screenshots/current-UI*.png；pnpm --filter @apps/web typecheck 通过。
A65: DEV-061 | B65: 主游戏UI | C65: UI05 局势记录 | D65: SituationRecord | E65: 按现有古典三栏设计接入真实公共投影和状态机，保持顶部/左右栏稳定。 | F65: 中间覆盖、筛选记录、关闭恢复scrollTop。 | G65: 11 UI§10 | H65: P0 | I65: 是 | J65: 待审核 | K65: =IF(J65="不适用","",IF(J65="已完成",1,IF(J65="待审核",0.9,IF(J65="进行中",0.5,IF(J65="已阻塞",0.25,0))))) -> 0.9 | L65: GET run/API公共投影 | M65: 第3天 | N65: Codex | O65: =总览!$C$5+2 -> 46217 | Q65: 页面与组件实现、现有截图和前端语法校验均存在；最终 P0 视觉验收仍未全部完成。 | R65: 在 Vercel 预览/正式域名执行全页面视觉与交互验收。 | S65: apps/web/public；docs/auto-execute/screenshots/current-UI*.png；pnpm --filter @apps/web typecheck 通过。
A66: DEV-062 | B66: 主游戏UI | C66: UI06 关键事件 | D66: CriticalEventModal | E66: 按现有古典三栏设计接入真实公共投影和状态机，保持顶部/左右栏稳定。 | F66: 页面压暗，仅立即处理/稍后处理。 | G66: 11 UI§11 | H66: P0 | I66: 是 | J66: 待审核 | K66: =IF(J66="不适用","",IF(J66="已完成",1,IF(J66="待审核",0.9,IF(J66="进行中",0.5,IF(J66="已阻塞",0.25,0))))) -> 0.9 | L66: GET run/API公共投影 | M66: 第3天 | N66: Codex | O66: =总览!$C$5+2 -> 46217 | Q66: 页面与组件实现、现有截图和前端语法校验均存在；最终 P0 视觉验收仍未全部完成。 | R66: 在 Vercel 预览/正式域名执行全页面视觉与交互验收。 | S66: apps/web/public；docs/auto-execute/screenshots/current-UI*.png；pnpm --filter @apps/web typecheck 通过。
A67: DEV-063 | B67: 主游戏UI | C67: UI07 他人影响回应 | D67: CriticalResponse | E67: 按现有古典三栏设计接入真实公共投影和状态机，保持顶部/左右栏稳定。 | F67: 角色视角故事+A/B/C回应+自定义输入。 | G67: 11 UI§12 | H67: P0 | I67: 是 | J67: 待审核 | K67: =IF(J67="不适用","",IF(J67="已完成",1,IF(J67="待审核",0.9,IF(J67="进行中",0.5,IF(J67="已阻塞",0.25,0))))) -> 0.9 | L67: GET run/API公共投影 | M67: 第3天 | N67: Codex | O67: =总览!$C$5+2 -> 46217 | Q67: 页面与组件实现、现有截图和前端语法校验均存在；最终 P0 视觉验收仍未全部完成。 | R67: 在 Vercel 预览/正式域名执行全页面视觉与交互验收。 | S67: apps/web/public；docs/auto-execute/screenshots/current-UI*.png；pnpm --filter @apps/web typecheck 通过。
... A84: DEV-080 | B84: 主线决策 | C84: 因果来源 | D84: originEventId与FateSeed | E84: 实现DecisionService、ActionGuard、规则补丁、事件落账和公共投影。 | F84: 所有延迟帮助/反噬和结局解释可回溯到真实事件。 | G84: 04验收§5 | H84: P0 | I84: 是 | J84: 已完成 | K84: =IF(J84="不适用","",IF(J84="已完成",1,IF(J84="待审核",0.9,IF(J84="进行中",0.5,IF(J84="已阻塞",0.25,0))))) -> 1 | L84: API/数据库/剧本配置 | M84: 第3天 | N84: Codex | O84: =总览!$C$5+2 -> 46217 | Q84: 主线决策、主动谋划、关键事件、跨日和最终裁决均有当前因果运行时与 API 全流程测试证据。 | R84: 保留真实用户场景与发布后回归。 | S84: apps/api/src/mvp-causal-runtime.ts；apps/api/src/story.service.spec.ts；pnpm test:api 通过。
A85: DEV-081 | B85: 主动谋划与关键事件 | C85: 每日机会 | D85: 第1-6天每天2次，第7天0次 | E85: 实现ManeuverService、CriticalEvent队列、计数、Guard与事件投影。 | F85: 成功谋划扣1次，被拒不扣；未用不结转。 | G85: 01基线§8；02状态机§5.4 | H85: P0 | I85: 是 | J85: 已完成 | K85: =IF(J85="不适用","",IF(J85="已完成",1,IF(J85="待审核",0.9,IF(J85="进行中",0.5,IF(J85="已阻塞",0.25,0))))) -> 1 | L85: 决策系统/数据库/剧本配置 | M85: 第4天 | N85: Codex | O85: =总览!$C$5+3 -> 46218 | Q85: 主线决策、主动谋划、关键事件、跨日和最终裁决均有当前因果运行时与 API 全流程测试证据。 | R85: 保留真实用户场景与发布后回归。 | S85: apps/api/src/mvp-causal-runtime.ts；apps/api/src/story.service.spec.ts；pnpm test:api 通过。
A86: DEV-082 | B86: 主动谋划与关键事件 | C86: 人物交谈 | D86: contact | E86: 实现ManeuverService、CriticalEvent队列、计数、Guard与事件投影。 | F86: 支持目标角色和probe/request_intel/pressure/trade/custom意图。 | G86: 03 Schema§7 | H86: P0 | I86: 是 | J86: 已完成 | K86: =IF(J86="不适用","",IF(J86="已完成",1,IF(J86="待审核",0.9,IF(J86="进行中",0.5,IF(J86="已阻塞",0.25,0))))) -> 1 | L86: 决策系统/数据库/剧本配置 | M86: 第4天 | N86: Codex | O86: =总览!$C$5+3 -> 46218 | Q86: 主线决策、主动谋划、关键事件、跨日和最终裁决均有当前因果运行时与 API 全流程测试证据。 | R86: 保留真实用户场景与发布后回归。 | S86: apps/api/src/mvp-causal-runtime.ts；apps/api/src/story.service.spec.ts；pnpm test:api 通过。
A87: DEV-083 | B87: 主动谋划与关键事件 | C87: 派遣调查 | D87: investigate | E87: 实现ManeuverService、CriticalEvent队列、计数、Guard与事件投影。 | F87: 支持驿站、田契、粮仓、商会往来等配置化目标。 | G87: 03 Schema§7；10剧本§2.6 | H87: P0 | I87: 是 | J87: 已完成 | K87: =IF(J87="不适用","",IF(J87="已完成",1,IF(J87="待审核",0.9,IF(J87="进行中",0.5,IF(J87="已阻塞",0.25,0))))) -> 1 | L87: 决策系统/数据库/剧本配置 | M87: 第4天 | N87: Codex | O87: =总览!$C$5+3 -> 46218 | Q87: 主线决策、主动谋划、关键事件、跨日和最终裁决均有当前因果运行时与 API 全流程测试证据。 | R87: 保留真实用户场景与发布后回归。 | S87: apps/api/src/mvp-causal-runtime.ts；apps/api/src/story.service.spec.ts；pnpm test:api 通过。
A88: DEV-084 | B88: 主动谋划与关键事件 | C88: 使用筹码 | D88: leverage | E88: 实现ManeuverService、CriticalEvent队列、计数、Guard与事件投影。 | F88: 验证leverage所有权、目标、意图和singleUse状态。 | G88: 03 Schema§8 | H88: P0 | I88: 是 | J88: 已完成 | K88: =IF(J88="不适用","",IF(J88="已完成",1,IF(J88="待审核",0.9,IF(J88="进行中",0.5,IF(J88="已阻塞",0.25,0))))) -> 1 | L88: 决策系统/数据库/剧本配置 | M88: 第4天 | N88: Codex | O88: =总览!$C$5+3 -> 46218 | Q88: 主线决策、主动谋划、关键事件、跨日和最终裁决均有当前因果运行时与 API 全流程测试证据。 | R88: 保留真实用户场景与发布后回归。 | S88: apps/api/src/mvp-causal-runtime.ts；apps/api/src/story.service.spec.ts；pnpm test:api 通过。
A89: DEV-085 | B89: 主动谋划与关键事件 | C89: 自拟谋划 | D89: custom | E89: 实现ManeuverService、CriticalEvent队列、计数、Guard与事件投影。 | F89: 1-200字并经过ActionGuard。 | G89: 02状态机§9.10 | H89: P0 | I89: 是 | J89: 已完成 | K89: =IF(J89="不适用","",IF(J89="已完成",1,IF(J89="待审核",0.9,IF(J89="进行中",0.5,IF(J89="已阻塞",0.25,0))))) -> 1 | L89: 决策系统/数据库/剧本配置 | M89: 第4天 | N89: Codex | O89: =总览!$C$5+3 -> 46218 | Q89: 主线决策、主动谋划、关键事件、跨日和最终裁决均有当前因果运行时与 API 全流程测试证据。 | R89: 保留真实用户场景与发布后回归。 | S89: apps/api/src/mvp-causal-runtime.ts；apps/api/src/story.service.spec.ts；pnpm test:api 通过。
A90: DEV-086 | B90: 主动谋划与关键事件 | C90: 谋划结果 | D90: maneuver_result | E90: 实现ManeuverService、CriticalEvent队列、计数、Guard与事件投影。 | F90: 追加结果故事、可见变化、FateSeed/痕迹和必要角色反应。 | G90: 08数据库§8.6 | H90: P0 | I90: 是 | J90: 已完成 | K90: =IF(J90="不适用","",IF(J90="已完成",1,IF(J90="待审核",0.9,IF(J90="进行中",0.5,IF(J90="已阻塞",0.25,0))))) -> 1 | L90: 决策系统/数据库/剧本配置 | M90: 第4天 | N90: Codex | O90: =总览!$C$5+3 -> 46218 | Q90: 主线决策、主动谋划、关键事件、跨日和最终裁决均有当前因果运行时与 API 全流程测试证据。 | R90: 保留真实用户场景与发布后回归。 | S90: apps/api/src/mvp-causal-runtime.ts；apps/api/src/story.service.spec.ts；pnpm test:api 通过。
A91: DEV-087 | B91: 主动谋划与关键事件 | C91: 状态许可 | D91: 仅awaiting_decision/day_advance可用 | E91: 实现ManeuverService、CriticalEvent队列、计数、Guard与事件投影。 | F91: resolving/day7/finished拒绝。 | G91: 02状态机§2-4 | H91: P0 | I91: 是 | J91: 已完成 | K91: =IF(J91="不适用","",IF(J91="已完成",1,IF(J91="待审核",0.9,IF(J91="进行中",0.5,IF(J91="已阻塞",0.25,0))))) -> 1 | L91: 决策系统/数据库/剧本配置 | M91: 第4天 | N91: Codex | O91: =总览!$C$5+3 -> 46218 | Q91: 主线决策、主动谋划、关键事件、跨日和最终裁决均有当前因果运行时与 API 全流程测试证据。 | R91: 保留真实用户场景与发布后回归。 | S91: apps/api/src/mvp-causal-runtime.ts；apps/api/src/story.service.spec.ts；pnpm test:api 通过。
A92: DEV-088 | B92: 主动谋划与关键事件 | C92: 主线隔离 | D92: 谋划不能解决activePrompt | E92: 实现ManeuverService、CriticalEvent队列、计数、Guard与事件投影。 | F92: 不修改decisionsCompletedToday，不替代每天2次主线决策。 | G92: 01基线§8；04验收M-009 | H92: P0 | I92: 是 | J92: 已完成 | K92: =IF(J92="不适用","",IF(J92="已完成",1,IF(J92="待审核",0.9,IF(J92="进行中",0.5,IF(J92="已阻塞",0.25,0))))) -> 1 | L92: 决策系统/数据库/剧本配置 | M92: 第4天 | N92: Codex | O92: =总览!$C$5+3 -> 46218 | Q92: 主线决策、主动谋划、关键事件、跨日和最终裁决均有当前因果运行时与 API 全流程测试证据。 | R92: 保留真实用户场景与发布后回归。 | S92: apps/api/src/mvp-causal-runtime.ts；apps/api/src/story.service.spec.ts；pnpm test:api 通过。
A93: DEV-089 | B93: 主动谋划与关键事件 | C93: 跨日重置 | D93: advance-day重置机会 | E93: 实现ManeuverService、CriticalEvent队列、计数、Guard与事件投影。 | F93: 上一日未用作废，新日used=0/remaining=2。 | G93: 02状态机§9.11 | H93: P0 | I93: 是 | J93: 已完成 | K93: =IF(J93="不适用","",IF(J93="已完成",1,IF(J93="待审核",0.9,IF(J93="进行中",0.5,IF(J93="已阻塞",0.25,0))))) -> 1 | L93: 决策系统/数据库/剧本配置 | M93: 第4天 | N93: Codex | O93: =总览!$C$5+3 -> 46218 | Q93: 主线决策、主动谋划、关键事件、跨日和最终裁决均有当前因果运行时与 API 全流程测试证据。 | R93: 保留真实用户场景与发布后回归。 | S93: apps/api/src/mvp-causal-runtime.ts；apps/api/src/story.service.spec.ts；pnpm test:api 通过。
A94: DEV-090 | B94: 主动谋划与关键事件 | C94: 关键事件生成 | D94: critical_event | E94: 实现ManeuverService、CriticalEvent队列、计数、Guard与事件投影。 | F94: 仅直接影响玩家且requiresResponse/high时弹窗。 | G94: 11 UI§11 | H94: P0 | I94: 是 | J94: 已完成 | K94: =IF(J94="不适用","",IF(J94="已完成",1,IF(J94="待审核",0.9,IF(J94="进行中",0.5,IF(J94="已阻塞",0.25,0))))) -> 1 | L94: 决策系统/数据库/剧本配置 | M94: 第4天 | N94: Codex | O94: =总览!$C$5+3 -> 46218 | Q94: 主线决策、主动谋划、关键事件、跨日和最终裁决均有当前因果运行时与 API 全流程测试证据。 | R94: 保留真实用户场景与发布后回归。 | S94: apps/api/src/mvp-causal-runtime.ts；apps/api/src/story.service.spec.ts；pnpm test:api 通过。
A95: DEV-091 | B95: 主动谋划与关键事件 | C95: 稍后处理 | D95: critical_event_deferred | E95: 实现ManeuverService、CriticalEvent队列、计数、Guard与事件投影。 | F95: 追加事件并恢复待处理标记，不完成决策。 | G95: 02状态机§9.9 | H95: P0 | I95: 是 | J95: 已完成 | K95: =IF(J95="不适用","",IF(J95="已完成",1,IF(J95="待审核",0.9,IF(J95="进行中",0.5,IF(J95="已阻塞",0.25,0))))) -> 1 | L95: 决策系统/数据库/剧本配置 | M95: 第4天 | N95: Codex | O95: =总览!$C$5+3 -> 46218 | Q95: 主线决策、主动谋划、关键事件、跨日和最终裁决均有当前因果运行时与 API 全流程测试证据。 | R95: 保留真实用户场景与发布后回归。 | S95: apps/api/src/mvp-causal-runtime.ts；apps/api/src/story.service.spec.ts；pnpm test:api 通过。
A96: DEV-092 | B96: 主动谋划与关键事件 | C96: 立即处理 | D96: critical_response提升为activePrompt | E96: 实现ManeuverService、CriticalEvent队列、计数、Guard与事件投影。 | F96: 占用当日固定主线槽位，不额外增加12次总数。 | G96: 01基线§8；02状态机§2 | H96: P0 | I96: 是 | J96: 已完成 | K96: =IF(J96="不适用","",IF(J96="已完成",1,IF(J96="待审核",0.9,IF(J96="进行中",0.5,IF(J96="已阻塞",0.25,0))))) -> 1 | L96: 决策系统/数据库/剧本配置 | M96: 第4天 | N96: Codex | O96: =总览!$C$5+3 -> 46218 | Q96: 主线决策、主动谋划、关键事件、跨日和最终裁决均有当前因果运行时与 API 全流程测试证据。 | R96: 保留真实用户场景与发布后回归。 | S96: apps/api/src/mvp-causal-runtime.ts；apps/api/src/story.service.spec.ts；pnpm test:api 通过。
... A120: DEV-116 | B120: 支付与权益 | C120: 支付入口 | D120: 前端购买页/按钮 | E120: 实现Creem服务端客户端、Webhook、支付事件和用户权益。 | F120: 登录用户发起购买；成功/取消页面明确。 | G120: Creem审核 | H120: P0 | I120: 是 | J120: 待审核 | K120: =IF(J120="不适用","",IF(J120="已完成",1,IF(J120="待审核",0.9,IF(J120="进行中",0.5,IF(J120="已阻塞",0.25,0))))) -> 0.9 | L120: 登录/数据库/公网后端 | M120: 第4天 | N120: Codex+我 | O120: =总览!$C$5+3 -> 46218 | Q120: 本地测试 Checkout、Webhook、购买页和回跳页实现已具备；Creem Dashboard 最终证据与 Vercel 正式部署尚未完成。 | R120: 配置 Railway/Vercel 域名与 Creem webhook 后执行真实 Test Mode 全链路验证。 | S120: apps/api/src/billing；apps/web/public/js/credits*.js；docs/auto-execute/world-credits/11-final-acceptance-report.md
A121: DEV-117 | B121: 支付与权益 | C121: Webhook | D121: 接收checkout.completed/refund/dispute | E121: 实现Creem服务端客户端、Webhook、支付事件和用户权益。 | F121: 公网HTTPS完整路径，校验签名和原始请求体。 | G121: 现有API调试文档 | H121: P0 | I121: 是 | J121: 进行中 | K121: =IF(J121="不适用","",IF(J121="已完成",1,IF(J121="待审核",0.9,IF(J121="进行中",0.5,IF(J121="已阻塞",0.25,0))))) -> 0.5 | L121: 登录/数据库/公网后端 | M121: 第4天 | N121: Codex+我 | O121: =总览!$C$5+3 -> 46218
A122: DEV-118 | B122: 支付与权益 | C122: 支付幂等 | D122: payment_events唯一 | E122: 实现Creem服务端客户端、Webhook、支付事件和用户权益。 | F122: 重复Webhook不重复增加Credits/权益。 | G122: 并发与幂等原则 | H122: P0 | I122: 是 | J122: 未开始 | K122: =IF(J122="不适用","",IF(J122="已完成",1,IF(J122="待审核",0.9,IF(J122="进行中",0.5,IF(J122="已阻塞",0.25,0))))) -> 0 | L122: 登录/数据库/公网后端 | M122: 第4天 | N122: Codex+我 | O122: =总览!$C$5+3 -> 46218
A123: DEV-119 | B123: 支付与权益 | C123: 权益发放 | D123: entitlements/credits | E123: 实现Creem服务端客户端、Webhook、支付事件和用户权益。 | F123: 支付成功后绑定userId并在账户页显示。 | G123: Creem闭环 | H123: P0 | I123: 是 | J123: 未开始 | K123: =IF(J123="不适用","",IF(J123="已完成",1,IF(J123="待审核",0.9,IF(J123="进行中",0.5,IF(J123="已阻塞",0.25,0))))) -> 0 | L123: 登录/数据库/公网后端 | M123: 第4天 | N123: Codex+我 | O123: =总览!$C$5+3 -> 46218
A124: DEV-120 | B124: 支付与权益 | C124: 退款撤销 | D124: refund/dispute处理 | E124: 实现Creem服务端客户端、Webhook、支付事件和用户权益。 | F124: 按政策回收未使用权益或标记人工处理。 | G124: Refund Policy | H124: P1 | I124: 否 | J124: 未开始 | K124: =IF(J124="不适用","",IF(J124="已完成",1,IF(J124="待审核",0.9,IF(J124="进行中",0.5,IF(J124="已阻塞",0.25,0))))) -> 0 | L124: 登录/数据库/公网后端 | M124: 第4天 | N124: Codex+我 | O124: =总览!$C$5+3 -> 46218
A125: DEV-121 | B125: 支付与权益 | C125: Live切换 | D125: Test与Live配置隔离 | E125: 实现Creem服务端客户端、Webhook、支付事件和用户权益。 | F125: Live通过后重新配置产品ID/API Key/Webhook Secret。 | G125: Creem环境隔离 | H125: P0 | I125: 是 | J125: 未开始 | K125: =IF(J125="不适用","",IF(J125="已完成",1,IF(J125="待审核",0.9,IF(J125="进行中",0.5,IF(J125="已阻塞",0.25,0))))) -> 0 | L125: 登录/数据库/公网后端 | M125: 第4天 | N125: Codex+我 | O125: =总览!$C$5+3 -> 46218
A126: DEV-122 | B126: 安全与可观测性 | C126: 产品埋点 | D126: 核心漏斗事件 | E126: 完成埋点、日志、监控、安全头、限流和密钥治理。 | F126: 记录lobby、role、run、decision、simulation、change、maneuver、day、ending、replay。 | G126: 06试玩§5 | H126: P1 | I126: 否 | J126: 未开始 | K126: =IF(J126="不适用","",IF(J126="已完成",1,IF(J126="待审核",0.9,IF(J126="进行中",0.5,IF(J126="已阻塞",0.25,0))))) -> 0 | L126: 核心API/部署 | M126: 第5天 | N126: Codex+我 | O126: =总览!$C$5+4 -> 46219
A127: DEV-123 | B127: 安全与可观测性 | C127: 隐私埋点 | D127: 不上传完整自定义文本 | E127: 完成埋点、日志、监控、安全头、限流和密钥治理。 | F127: 只上传字数、分类、是否编辑和hash。 | G127: 06试玩§5 | H127: P1 | I127: 否 | J127: 未开始 | K127: =IF(J127="不适用","",IF(J127="已完成",1,IF(J127="待审核",0.9,IF(J127="进行中",0.5,IF(J127="已阻塞",0.25,0))))) -> 0 | L127: 核心API/部署 | M127: 第5天 | N127: Codex+我 | O127: =总览!$C$5+4 -> 46219
A128: DEV-124 | B128: 安全与可观测性 | C128: 结构化日志 | D128: requestId/runId/eventId/version/fallback | E128: 完成埋点、日志、监控、安全头、限流和密钥治理。 | F128: 日志能定位单局失败，敏感字段脱敏。 | G128: 05部署§8 | H128: P0 | I128: 是 | J128: 未开始 | K128: =IF(J128="不适用","",IF(J128="已完成",1,IF(J128="待审核",0.9,IF(J128="进行中",0.5,IF(J128="已阻塞",0.25,0))))) -> 0 | L128: 核心API/部署 | M128: 第5天 | N128: Codex+我 | O128: =总览!$C$5+4 -> 46219
A129: DEV-125 | B129: 安全与可观测性 | C129: 错误监控 | D129: Sentry或同类 | E129: 完成埋点、日志、监控、安全头、限流和密钥治理。 | F129: 捕获前后端异常和部署版本。 | G129: 05部署§11 | H129: P1 | I129: 否 | J129: 未开始 | K129: =IF(J129="不适用","",IF(J129="已完成",1,IF(J129="待审核",0.9,IF(J129="进行中",0.5,IF(J129="已阻塞",0.25,0))))) -> 0 | L129: 核心API/部署 | M129: 第5天 | N129: Codex+我 | O129: =总览!$C$5+4 -> 46219
A130: DEV-126 | B130: 安全与可观测性 | C130: 核心指标 | D130: API/AI/成本/恢复 | E130: 完成埋点、日志、监控、安全头、限流和密钥治理。 | F130: 监控5xx、延迟、AI超时、fallback、冲突、恢复、单局成本。 | G130: 05部署§11 | H130: P1 | I130: 否 | J130: 未开始 | K130: =IF(J130="不适用","",IF(J130="已完成",1,IF(J130="待审核",0.9,IF(J130="进行中",0.5,IF(J130="已阻塞",0.25,0))))) -> 0 | L130: 核心API/部署 | M130: 第5天 | N130: Codex+我 | O130: =总览!$C$5+4 -> 46219
A131: DEV-127 | B131: 安全与可观测性 | C131: 告警 | D131: 配置高优先级告警 | E131: 完成埋点、日志、监控、安全头、限流和密钥治理。 | F131: 私密字段泄露、存储失败、finalize失败和成本超限立即告警。 | G131: 05部署§11.2 | H131: P1 | I131: 否 | J131: 未开始 | K131: =IF(J131="不适用","",IF(J131="已完成",1,IF(J131="待审核",0.9,IF(J131="进行中",0.5,IF(J131="已阻塞",0.25,0))))) -> 0 | L131: 核心API/部署 | M131: 第5天 | N131: Codex+我 | O131: =总览!$C$5+4 -> 46219
A132: DEV-128 | B132: 安全与可观测性 | C132: CORS/CSP | D132: 限制来源与脚本 | E132: 完成埋点、日志、监控、安全头、限流和密钥治理。 | F132: 生产仅允许正式域名；CSP减少XSS风险。 | G132: 05部署§10 | H132: P0 | I132: 是 | J132: 未开始 | K132: =IF(J132="不适用","",IF(J132="已完成",1,IF(J132="待审核",0.9,IF(J132="进行中",0.5,IF(J132="已阻塞",0.25,0))))) -> 0 | L132: 核心API/部署 | M132: 第5天 | N132: Codex+我 | O132: =总览!$C$5+4 -> 46219
A133: DEV-129 | B133: 安全与可观测性 | C133: 请求限流 | D133: API与AI限流 | E133: 完成埋点、日志、监控、安全头、限流和密钥治理。 | F133: 按用户/IP限制创建局、提交和模型调用。 | G133: 05部署§10 | H133: P1 | I133: 否 | J133: 未开始 | K133: =IF(J133="不适用","",IF(J133="已完成",1,IF(J133="待审核",0.9,IF(J133="进行中",0.5,IF(J133="已阻塞",0.25,0))))) -> 0 | L133: 核心API/部署 | M133: 第5天 | N133: Codex+我 | O133: =总览!$C$5+4 -> 46219
A134: DEV-130 | B134: 安全与可观测性 | C134: 密钥管理 | D134: 密钥不入库 | E134: 完成埋点、日志、监控、安全头、限流和密钥治理。 | F134: Vercel/Railway/Supabase环境变量保存，日志与前端不显示。 | G134: 05部署§2 | H134: P0 | I134: 是 | J134: 未开始 | K134: =IF(J134="不适用","",IF(J134="已完成",1,IF(J134="待审核",0.9,IF(J134="进行中",0.5,IF(J134="已阻塞",0.25,0))))) -> 0 | L134: 核心API/部署 | M134: 第5天 | N134: Codex+我 | O134: =总览!$C$5+4 -> 46219
A135: DEV-131 | B135: 安全与可观测性 | C135: 健康与状态 | D135: 状态页/客服信息 | E135: 完成埋点、日志、监控、安全头、限流和密钥治理。 | F135: 上线时用户能获知服务异常和联系支持。 | G135: 上线运营要求 | H135: P1 | I135: 否 | J135: 未开始 | K135: =IF(J135="不适用","",IF(J135="已完成",1,IF(J135="待审核",0.9,IF(J135="进行中",0.5,IF(J135="已阻塞",0.25,0))))) -> 0 | L135: 核心API/部署 | M135: 第5天 | N135: Codex+我 | O135: =总览!$C$5+4 -> 46219
A136: DEV-132 | B136: 部署与发布 | C136: 前端构建 | D136: Vercel部署apps/web | E136: 按部署方案配置服务、环境变量、数据迁移、监控、回滚和上线冒烟。 | F136: 生产构建通过，域名、HTTPS、环境变量和缓存正确。 | G136: 部署方案 | H136: P0 | I136: 是 | J136: 未开始 | K136: =IF(J136="不适用","",IF(J136="已完成",1,IF(J136="待审核",0.9,IF(J136="进行中",0.5,IF(J136="已阻塞",0.25,0))))) -> 0 | L136: P0功能完成 | M136: 第6天 | N136: Codex+我 | O136: =总览!$C$5+5 -> 46220
A137: DEV-133 | B137: 部署与发布 | C137: 后端构建 | D137: 部署NestJS API | E137: 按部署方案配置服务、环境变量、数据迁移、监控、回滚和上线冒烟。 | F137: 推荐Railway/Render运行现有apps/api；配置health check和自动重启。 | G137: 05部署§14 | H137: P0 | I137: 是 | J137: 未开始 | K137: =IF(J137="不适用","",IF(J137="已完成",1,IF(J137="待审核",0.9,IF(J137="进行中",0.5,IF(J137="已阻塞",0.25,0))))) -> 0 | L137: P0功能完成 | M137: 第6天 | N137: Codex+我 | O137: =总览!$C$5+5 -> 46220
A138: DEV-134 | B138: 部署与发布 | C138: 数据库 | D138: Supabase生产数据库 | E138: 按部署方案配置服务、环境变量、数据迁移、监控、回滚和上线冒烟。 | F138: 执行迁移、RLS、连接池、备份和生产密钥。 | G138: 08数据库；05部署§12 | H138: P0 | I138: 是 | J138: 未开始 | K138: =IF(J138="不适用","",IF(J138="已完成",1,IF(J138="待审核",0.9,IF(J138="进行中",0.5,IF(J138="已阻塞",0.25,0))))) -> 0 | L138: P0功能完成 | M138: 第6天 | N138: Codex+我 | O138: =总览!$C$5+5 -> 46220
A139: DEV-135 | B139: 部署与发布 | C139: 域名路由 | D139: 配置Web/API域名与CORS | E139: 按部署方案配置服务、环境变量、数据迁移、监控、回滚和上线冒烟。 | F139: ourmanyworlds.com指向Web；api子域或反向代理指向API。 | G139: 部署方案 | H139: P0 | I139: 是 | J139: 未开始 | K139: =IF(J139="不适用","",IF(J139="已完成",1,IF(J139="待审核",0.9,IF(J139="进行中",0.5,IF(J139="已阻塞",0.25,0))))) -> 0 | L139: P0功能完成 | M139: 第6天 | N139: Codex+我 | O139: =总览!$C$5+5 -> 46220
A140: DEV-136 | B140: 部署与发布 | C140: Staging | D140: 建立独立staging | E140: 按部署方案配置服务、环境变量、数据迁移、监控、回滚和上线冒烟。 | F140: 独立URL、数据库、Creem Test、AI预算；供20局验收。 | G140: 05部署§1 | H140: P0 | I140: 是 | J140: 未开始 | K140: =IF(J140="不适用","",IF(J140="已完成",1,IF(J140="待审核",0.9,IF(J140="进行中",0.5,IF(J140="已阻塞",0.25,0))))) -> 0 | L140: P0功能完成 | M140: 第6天 | N140: Codex+我 | O140: =总览!$C$5+5 -> 46220
...

Sheet 测试进度
A1: AI多人剧情推演｜MVP测试进度
A3: 已将自动化验收矩阵完整拆入本表，并补充登录、创建/进入房间、Supabase权限、Creem支付和部署冒烟测试。P0测试未全部通过前，不建议公开Limited Beta。
A4: 测试ID | B4: 测试层级 | C4: 模块 | D4: 场景/输入 | E4: 前置条件 | F4: 操作/步骤 | G4: 预期/断言 | H4: 优先级 | I4: 上线阻断 | J4: 状态 | K4: 自动化 | L4: 建议工具 | M4: 计划阶段 | N4: 负责人 | O4: 计划日期 | P4: 实际日期 | Q4: 缺陷ID | R4: 证据/备注
A5: F-001 | B5: Service/HTTP | C5: 功能测试 | D5: 创建新局 | E5: 无 | F5: POST create | G5: 201；第 1 天；`awaiting_decision`；version=1 | H5: P0 | I5: 是 | J5: 未执行 | K5: 自动 | L5: Vitest/Nest/fetch | M5: 第5天 | N5: Codex | O5: =总览!$C$5+4 -> 46219
A6: F-002 | B6: Service/HTTP | C6: 功能测试 | D6: 恢复新局 | E6: 已有 runId | F6: GET run | G6: 返回相同状态与 activePrompt | H6: P0 | I6: 是 | J6: 未执行 | K6: 自动 | L6: Vitest/Nest/fetch | M6: 第5天 | N6: Codex | O6: =总览!$C$5+4 -> 46219
A7: F-003 | B7: Service/HTTP | C7: 功能测试 | D7: 第一次预设决策 | E7: awaiting_decision | F7: 选 A | G7: 写入 1 次 decision；version+1；生成结果消息 | H7: P0 | I7: 是 | J7: 未执行 | K7: 自动 | L7: Vitest/Nest/fetch | M7: 第5天 | N7: Codex | O7: =总览!$C$5+4 -> 46219
A8: F-004 | B8: Service/HTTP | C8: 功能测试 | D8: 第二次决策 | E8: 当日已完成 1 次 | F8: 再选 | G8: 当日完成 2 次；生成 day_end；进入 awaiting_day_advance | H8: P0 | I8: 是 | J8: 未执行 | K8: 自动 | L8: Vitest/Nest/fetch | M8: 第5天 | N8: Codex | O8: =总览!$C$5+4 -> 46219
A9: F-005 | B9: Service/HTTP | C9: 功能测试 | D9: 未完成当天推进 | E9: 只完成 1 次 | F9: advance-day | G9: 409 DAY_NOT_COMPLETE | H9: P0 | I9: 是 | J9: 未执行 | K9: 自动 | L9: Vitest/Nest/fetch | M9: 第5天 | N9: Codex | O9: =总览!$C$5+4 -> 46219
A10: F-006 | B10: Service/HTTP | C10: 功能测试 | D10: 正常推进 | E10: awaiting_day_advance | F10: advance-day | G10: 下一天；decision 计数清零；新 activePrompt | H10: P0 | I10: 是 | J10: 未执行 | K10: 自动 | L10: Vitest/Nest/fetch | M10: 第5天 | N10: Codex | O10: =总览!$C$5+4 -> 46219
A11: F-007 | B11: Service/HTTP | C11: 功能测试 | D11: 12 次决策闭环 | E11: 第 1 天 | F11: 连续完成 6 天 | G11: 共 12 次；无丢失、无重复 | H11: P0 | I11: 是 | J11: 未执行 | K11: 自动 | L11: Vitest/Nest/fetch | M11: 第5天 | N11: Codex | O11: =总览!$C$5+4 -> 46219
A12: F-008 | B12: Service/HTTP | C12: 功能测试 | D12: 第 7 天状态 | E12: 第 6 天完成并推进 | F12: GET run | G12: currentDay=7；awaiting_finalization；activePrompt=null | H12: P0 | I12: 是 | J12: 未执行 | K12: 自动 | L12: Vitest/Nest/fetch | M12: 第5天 | N12: Codex | O12: =总览!$C$5+4 -> 46219
A13: F-009 | B13: Service/HTTP | C13: 功能测试 | D13: 提前 finalize | E13: 第 1—6 天 | F13: finalize | G13: 409 FINALIZATION_NOT_READY | H13: P0 | I13: 是 | J13: 未执行 | K13: 自动 | L13: Vitest/Nest/fetch | M13: 第5天 | N13: Codex | O13: =总览!$C$5+4 -> 46219
A14: F-010 | B14: Service/HTTP | C14: 功能测试 | D14: 正常 finalize | E14: 第 7 天 ready | F14: finalize | G14: finished；完整 finalJudgement | H14: P0 | I14: 是 | J14: 未执行 | K14: 自动 | L14: Vitest/Nest/fetch | M14: 第5天 | N14: Codex | O14: =总览!$C$5+4 -> 46219
A15: F-011 | B15: Service/HTTP | C15: 功能测试 | D15: finished 后再决策 | E15: finished | F15: submit decision | G15: 409 INVALID_RUN_STATE | H15: P0 | I15: 是 | J15: 未执行 | K15: 自动 | L15: Vitest/Nest/fetch | M15: 第5天 | N15: Codex | O15: =总览!$C$5+4 -> 46219
A16: F-012 | B16: Service/HTTP | C16: 功能测试 | D16: 重开一局 | E16: 任意旧局 | F16: create 新 run | G16: 新 runId；旧局不被覆盖 | H16: P0 | I16: 是 | J16: 未执行 | K16: 自动 | L16: Vitest/Nest/fetch | M16: 第5天 | N16: Codex | O16: =总览!$C$5+4 -> 46219
... A29: F-025 | B29: Service/HTTP | C29: 功能测试 | D29: 使用筹码 | E29: leverage 可用 | F29: POST leverage maneuver | G29: 写入 `leverage_used`；筹码状态按规则变化 | H29: P0 | I29: 是 | J29: 未执行 | K29: 自动 | L29: Vitest/Nest/fetch | M29: 第5天 | N29: Codex | O29: =总览!$C$5+4 -> 46219
A30: G-001 | B30: Unit/Service | C30: ActionGuard | D30: “不拦急奏，另写密奏” | G30: `ok` | H30: P0 | I30: 是 | J30: 未执行 | K30: 自动 | L30: Vitest | M30: 第5天 | N30: Codex | O30: =总览!$C$5+4 -> 46219
A31: G-002 | B31: Unit/Service | C31: ActionGuard | D31: “派幕僚查驿站登记” | G31: `ok` 或 `soft_warn` | H31: P0 | I31: 是 | J31: 未执行 | K31: 自动 | L31: Vitest | M31: 第5天 | N31: Codex | O31: =总览!$C$5+4 -> 46219
A32: G-003 | B32: Unit/Service | C32: ActionGuard | D32: “命令皇帝立即处死巡抚” | G32: `blocked`：越权且操控他人 | H32: P0 | I32: 是 | J32: 未执行 | K32: 自动 | L32: Vitest | M32: 第5天 | N32: Codex | O32: =总览!$C$5+4 -> 46219
A33: G-004 | B33: Unit/Service | C33: ActionGuard | D33: “我宣布巡抚已经认罪” | G33: `blocked`：直接宣布结果 | H33: P0 | I33: 是 | J33: 未执行 | K33: 自动 | L33: Vitest | M33: 第5天 | N33: Codex | O33: =总览!$C$5+4 -> 46219
A34: G-005 | B34: Unit/Service | C34: ActionGuard | D34: “凭空拿出完整暗账” | G34: `rewrite_needed`：不存在的证据 | H34: P0 | I34: 是 | J34: 未执行 | K34: 自动 | L34: Vitest | M34: 第5天 | N34: Codex | O34: =总览!$C$5+4 -> 46219
A35: G-006 | B35: Unit/Service | C35: ActionGuard | D35: “跳到第 7 天直接裁决” | G35: `blocked`：跳过阶段 | H35: P0 | I35: 是 | J35: 未执行 | K35: 自动 | L35: Vitest | M35: 第5天 | N35: Codex | O35: =总览!$C$5+4 -> 46219
A36: G-007 | B36: Unit/Service | C36: ActionGuard | D36: “调一百万兵围困京师” | G36: `blocked`：资源与时代权限不符 | H36: P0 | I36: 是 | J36: 未执行 | K36: 自动 | L36: Vitest | M36: 第5天 | N36: Codex | O36: =总览!$C$5+4 -> 46219
A37: G-008 | B37: Unit/Service | C37: ActionGuard | D37: 空 customText | G37: `400 CUSTOM_TEXT_REQUIRED` | H37: P0 | I37: 是 | J37: 未执行 | K37: 自动 | L37: Vitest | M37: 第5天 | N37: Codex | O37: =总览!$C$5+4 -> 46219
A38: G-009 | B38: Unit/Service | C38: ActionGuard | D38: 主线决策超过 200 字 | G38: `400 CUSTOM_TEXT_TOO_LONG` 或前端拒绝 | H38: P0 | I38: 是 | J38: 未执行 | K38: 自动 | L38: Vitest | M38: 第5天 | N38: Codex | O38: =总览!$C$5+4 -> 46219
A39: G-010 | B39: Unit/Service | C39: ActionGuard | D39: 合法但高风险交易 | G39: `soft_warn`，允许继续且提示风险 | H39: P0 | I39: 是 | J39: 未执行 | K39: 自动 | L39: Vitest | M39: 第5天 | N39: Codex | O39: =总览!$C$5+4 -> 46219
A40: G-011 | B40: Unit/Service | C40: ActionGuard | D40: 尝试控制县令具体结论 | G40: 规范化为“要求/试图”，不保证结果 | H40: P0 | I40: 是 | J40: 未执行 | K40: 自动 | L40: Vitest | M40: 第5天 | N40: Codex | O40: =总览!$C$5+4 -> 46219
A41: G-012 | B41: Unit/Service | C41: ActionGuard | D41: 重复提交被拒行动 | G41: 不消耗决策、不增加 version | H41: P0 | I41: 是 | J41: 未执行 | K41: 自动 | L41: Vitest | M41: 第5天 | N41: Codex | O41: =总览!$C$5+4 -> 46219
... A163: W-033 | B163: Web/E2E | C163: Web/UI | D163: 公共字段扫描 | G163: HTML/JSON 不包含 internalGain、internalRisk、statePatch 预测等字段 | H163: P0 | I163: 是 | J163: 未执行 | K163: 自动 | L163: Playwright/jsdom | M163: 第5-6天 | N163: Codex | O163: =总览!$C$5+4 -> 46219
A164: AUTH-001 | B164: HTTP/E2E | C164: 登录与账号 | D164: 新用户邮箱登录 | E164: 无账号 | F164: 输入邮箱并完成验证码/Magic Link | G164: 成功创建用户与会话，跳回原目标页面 | H164: P0 | I164: 是 | J164: 未执行 | K164: 半自动 | L164: Playwright/Supabase | M164: 第5天 | N164: Codex | O164: =总览!$C$5+4 -> 46219
A165: AUTH-002 | B165: HTTP/E2E | C165: 登录与账号 | D165: 已注册用户登录 | E165: 已有账号 | F165: 完成登录 | G165: 恢复同一userId和历史故事局 | H165: P0 | I165: 是 | J165: 未执行 | K165: 半自动 | L165: Playwright/Supabase | M165: 第5天 | N165: Codex | O165: =总览!$C$5+4 -> 46219
A166: AUTH-003 | B166: HTTP/E2E | C166: 登录与账号 | D166: 刷新保持会话 | E166: 已登录 | F166: 刷新页面/重开浏览器 | G166: 登录状态仍有效或自动刷新token | H166: P0 | I166: 是 | J166: 未执行 | K166: 半自动 | L166: Playwright/Supabase | M166: 第5天 | N166: Codex | O166: =总览!$C$5+4 -> 46219
A167: AUTH-004 | B167: HTTP/E2E | C167: 登录与账号 | D167: 过期会话 | E167: token过期 | F167: 访问受保护页面 | G167: 跳转登录，登录后返回原页面 | H167: P0 | I167: 是 | J167: 未执行 | K167: 半自动 | L167: Playwright/Supabase | M167: 第5天 | N167: Codex | O167: =总览!$C$5+4 -> 46219
A168: AUTH-005 | B168: HTTP/E2E | C168: 登录与账号 | D168: 退出登录 | E168: 已登录 | F168: 点击退出 | G168: 私有API不可访问，本地敏感会话被清除 | H168: P0 | I168: 是 | J168: 未执行 | K168: 半自动 | L168: Playwright/Supabase | M168: 第5天 | N168: Codex | O168: =总览!$C$5+4 -> 46219
A169: AUTH-006 | B169: HTTP/E2E | C169: 登录与账号 | D169: 未登录创建局 | E169: 未登录 | F169: POST create | G169: 401/跳转登录，不创建StoryRun | H169: P0 | I169: 是 | J169: 未执行 | K169: 半自动 | L169: Playwright/Supabase | M169: 第5天 | N169: Codex | O169: =总览!$C$5+4 -> 46219
A170: AUTH-007 | B170: HTTP/E2E | C170: 登录与账号 | D170: 越权读取他人run | E170: 用户A/B各有run | F170: B请求A的runId | G170: 404/403，不返回任何状态和事件 | H170: P0 | I170: 是 | J170: 未执行 | K170: 半自动 | L170: Playwright/Supabase | M170: 第5天 | N170: Codex | O170: =总览!$C$5+4 -> 46219
A171: AUTH-008 | B171: HTTP/E2E | C171: 登录与账号 | D171: 我的游戏列表隔离 | E171: 多用户多局 | F171: 获取recent runs | G171: 只返回当前用户的局 | H171: P0 | I171: 是 | J171: 未执行 | K171: 半自动 | L171: Playwright/Supabase | M171: 第5天 | N171: Codex | O171: =总览!$C$5+4 -> 46219
A172: AUTH-009 | B172: HTTP/E2E | C172: 登录与账号 | D172: 登录频率限制 | E172: 连续发送验证码 | F172: 快速重复请求 | G172: 返回429且不泄露账号存在性 | H172: P0 | I172: 是 | J172: 未执行 | K172: 半自动 | L172: Playwright/Supabase | M172: 第5天 | N172: Codex | O172: =总览!$C$5+4 -> 46219
A173: AUTH-010 | B173: HTTP/E2E | C173: 登录与账号 | D173: 账户删除申请 | E173: 有历史局/支付记录 | F173: 提交删除请求 | G173: 按策略删除或匿名化并保留必要审计 | H173: P1 | I173: 否 | J173: 未执行 | K173: 半自动 | L173: Playwright/Supabase | M173: 第5天 | N173: Codex | O173: =总览!$C$5+4 -> 46219
A174: ROOM-001 | B174: E2E | C174: 入口与房间 | D174: 从角色页开启房间 | E174: 已登录且选浙江总督 | F174: 点击开始 | G174: 只创建一个StoryRun并跳转/game?runId | H174: P0 | I174: 是 | J174: 未执行 | K174: 自动 | L174: Playwright/HTTP | M174: 第5天 | N174: Codex | O174: =总览!$C$5+4 -> 46219
A175: ROOM-002 | B175: E2E | C175: 入口与房间 | D175: 双击开启房间 | E175: 网络延迟 | F175: 连续点击开始 | G175: 幂等返回同一run，不创建重复局 | H175: P0 | I175: 是 | J175: 未执行 | K175: 自动 | L175: Playwright/HTTP | M175: 第5天 | N175: Codex | O175: =总览!$C$5+4 -> 46219
... A199: PAY-010 | B199: HTTP/E2E | C199: 支付与权益 | D199: 价格与权益一致 | E199: 官网/Creem/账户页 | F199: 人工核对 | G199: 商品名、$价格、权益与退款政策一致 | H199: P0 | I199: 是 | J199: 未执行 | K199: 半自动 | L199: Creem Test/HTTP | M199: 第5-6天 | N199: Codex+我 | O199: =总览!$C$5+4 -> 46219
A200: DEP-001 | B200: Smoke/Resilience | C200: 部署与运维 | D200: Vercel生产构建 | E200: 代码冻结 | F200: 执行build/deploy | G200: 构建通过，正式域名HTTPS可访问 | H200: P0 | I200: 是 | J200: 未执行 | K200: 半自动 | L200: CI/curl/Playwright | M200: 第6天 | N200: Codex+我 | O200: =总览!$C$5+5 -> 46220
A201: DEP-002 | B201: Smoke/Resilience | C201: 部署与运维 | D201: 后端健康检查 | E201: API已部署 | F201: GET /health | G201: 200，数据库依赖正常，无密钥泄露 | H201: P0 | I201: 是 | J201: 未执行 | K201: 半自动 | L201: CI/curl/Playwright | M201: 第6天 | N201: Codex+我 | O201: =总览!$C$5+5 -> 46220
A202: DEP-003 | B202: Smoke/Resilience | C202: 部署与运维 | D202: 数据库迁移 | E202: staging空库 | F202: 执行migration | G202: 表/索引/RLS创建成功，可回滚 | H202: P0 | I202: 是 | J202: 未执行 | K202: 半自动 | L202: CI/curl/Playwright | M202: 第6天 | N202: Codex+我 | O202: =总览!$C$5+5 -> 46220
A203: DEP-004 | B203: Smoke/Resilience | C203: 部署与运维 | D203: 环境隔离 | E203: staging/prod | F203: 对比配置 | G203: 数据库、Creem密钥、AI预算、日志完全隔离 | H203: P0 | I203: 是 | J203: 未执行 | K203: 半自动 | L203: CI/curl/Playwright | M203: 第6天 | N203: Codex+我 | O203: =总览!$C$5+5 -> 46220
A204: DEP-005 | B204: Smoke/Resilience | C204: 部署与运维 | D204: CORS正式域名 | E204: 生产API | F204: 从非法origin请求 | G204: 被拒；正式Web域名可正常调用 | H204: P0 | I204: 是 | J204: 未执行 | K204: 半自动 | L204: CI/curl/Playwright | M204: 第6天 | N204: Codex+我 | O204: =总览!$C$5+5 -> 46220
A205: DEP-006 | B205: Smoke/Resilience | C205: 部署与运维 | D205: 密钥扫描 | E205: 代码和构建产物 | F205: 运行secret scan | G205: 无API Key/service role/webhook secret入库 | H205: P0 | I205: 是 | J205: 未执行 | K205: 半自动 | L205: CI/curl/Playwright | M205: 第6天 | N205: Codex+我 | O205: =总览!$C$5+5 -> 46220
A206: DEP-007 | B206: Smoke/Resilience | C206: 部署与运维 | D206: 备份恢复 | E206: staging有测试局 | F206: 备份后恢复 | G206: StoryRun/StoryEvent/AiTask可恢复并继续 | H206: P0 | I206: 是 | J206: 未执行 | K206: 半自动 | L206: CI/curl/Playwright | M206: 第6天 | N206: Codex+我 | O206: =总览!$C$5+5 -> 46220
A207: DEP-008 | B207: Smoke/Resilience | C207: 部署与运维 | D207: 回滚演练 | E207: 部署新版本 | F207: 切回上一版本 | G207: 服务恢复，数据库兼容或按脚本回滚 | H207: P0 | I207: 是 | J207: 未执行 | K207: 半自动 | L207: CI/curl/Playwright | M207: 第6天 | N207: Codex+我 | O207: =总览!$C$5+5 -> 46220
A208: DEP-009 | B208: Smoke/Resilience | C208: 部署与运维 | D208: 上线冒烟 | E208: production | F208: 首页→登录→创建局→决策→刷新→恢复 | G208: 完整通过，无5xx | H208: P0 | I208: 是 | J208: 未执行 | K208: 半自动 | L208: CI/curl/Playwright | M208: 第6天 | N208: Codex+我 | O208: =总览!$C$5+5 -> 46220
A209: DEP-010 | B209: Smoke/Resilience | C209: 部署与运维 | D209: 监控与告警 | E209: 注入测试异常 | F209: 触发5xx/存储失败/私密字段 | G209: Sentry/告警渠道收到事件 | H209: P0 | I209: 是 | J209: 未执行 | K209: 半自动 | L209: CI/curl/Playwright | M209: 第6天 | N209: Codex+我 | O209: =总览!$C$5+5 -> 46220
A210: DEP-011 | B210: Smoke/Resilience | C210: 部署与运维 | D210: 海外访问 | E210: 海外网络 | F210: 访问Web/API/Creem | G210: 页面、登录、游戏和支付链接可访问 | H210: P0 | I210: 是 | J210: 未执行 | K210: 半自动 | L210: CI/curl/Playwright | M210: 第6天 | N210: Codex+我 | O210: =总览!$C$5+5 -> 46220
A211: DEP-012 | B211: Smoke/Resilience | C211: 部署与运维 | D211: 服务重启恢复 | E211: resolving/playing状态 | F211: 重启API | G211: 通过幂等账本恢复或fallback，不重复落账 | H211: P0 | I211: 是 | J211: 未执行 | K211: 半自动 | L211: CI/curl/Playwright | M211: 第6天 | N211: Codex+我 | O211: =总览!$C$5+5 -> 46220

Sheet 模拟对局
A1: AI多人剧情推演｜模拟对局与稳定性记录
A3: 模拟对局用于证明：12次主线决策、0—12次谋划、关键事件、并发、AI失败、刷新恢复、权限和支付闭环都能稳定完成。SIM-025要求连续20局无死路。
A4: 模拟ID | B4: 场景类型 | C4: 路径/故障注入 | D4: 主线决策策略 | E4: 谋划策略 | F4: 关键事件策略 | G4: 预期重点 | H4: 状态 | I4: 是否通过 | J4: 实际结局 | K4: 完成天数 | L4: 主线决策数 | M4: 谋划次数 | N4: AI调用数 | O4: 总Token | P4: 估算成本 | Q4: Fallback数 | R4: 耗时(分钟) | S4: 缺陷/异常 | T4: 证据/日志
A5: SIM-001 | B5: 主路径 | C5: 全A | D5: 每次选择A | E5: 不使用谋划 | F5: 立即处理 | G5: 状态签名A；到第7天；命中结局A；无死路 | H5: 未执行 | I5: 未执行
A6: SIM-002 | B6: 主路径 | C6: 全B | D6: 每次选择B | E6: 不使用谋划 | F6: 立即处理 | G6: 状态签名B；与全A至少一项结局/关键因果不同 | H6: 未执行 | I6: 未执行
A7: SIM-003 | B7: 主路径 | C7: 全C | D7: 每次选择C | E7: 不使用谋划 | F7: 立即处理 | G7: 状态签名C；与A/B存在差异 | H7: 未执行 | I7: 未执行
A8: SIM-004 | B8: 主路径 | C8: 混合路径 | D8: C,B,C,B,B,C,A,B,C,A,B,B | E8: 不使用谋划 | F8: 按配置 | G8: 12次主线完整；命中可解释结局 | H8: 未执行 | I8: 未执行
A9: SIM-005 | B9: 谋划路径 | C9: 零谋划 | D9: 混合主线 | E9: 每天0次 | F9: 立即处理 | G9: 仍可完成全局结局；未用机会不阻塞 | H9: 未执行 | I9: 未执行
A10: SIM-006 | B10: 谋划路径 | C10: 人物交谈 | D10: 混合主线 | E10: 每天1次contact | F10: 立即处理 | G10: 关系轨迹与零谋划不同 | H10: 未执行 | I10: 未执行
A11: SIM-007 | B11: 谋划路径 | C11: 调查 | D11: 混合主线 | E11: 每天1次investigate | F11: 立即处理 | G11: 线索/证据/FateSeed轨迹发生变化 | H11: 未执行 | I11: 未执行
A12: SIM-008 | B12: 谋划路径 | C12: 使用筹码 | D12: 混合主线 | E12: 每天1次leverage | F12: 立即处理 | G12: 筹码状态和责任/叙事定性变化 | H12: 未执行 | I12: 未执行
A13: SIM-009 | B13: 谋划路径 | C13: 满量谋划 | D13: 混合主线 | E13: 每天2次，共12次 | F13: 立即处理 | G13: 不能超过12次；每天重置；主线仍为12次 | H13: 未执行 | I13: 未执行
A14: SIM-010 | B14: 自定义输入 | C14: 全自定义合法行动 | D14: 每次使用合法自定义文本 | E14: 每天1次自拟谋划 | F14: 立即处理 | G14: ActionGuard允许；输出结构化；无越权 | H14: 未执行 | I14: 未执行
A15: SIM-011 | B15: 关键事件 | C15: 全部立即处理 | D15: 混合主线 | E15: 随机 | F15: 全部立即 | G15: critical_response计入主线槽位，总数仍12 | H15: 未执行 | I15: 未执行
A16: SIM-012 | B16: 关键事件 | C16: 延后再处理 | D16: 混合主线 | E16: 随机 | F16: 先延后，后处理 | G16: 刷新可恢复待处理；只落账一次 | H16: 未执行 | I16: 未执行
... A39: SIM-035 | B39: 备份 | C39: 从事件流重建快照 | D39: 完成到第5天 | E39: 随机 | F39: 随机 | G39: StoryRun与StoryEvent一致，activePrompt正确 | H39: 未执行 | I39: 未执行

Sheet 部署方案
A1: AI多人剧情推演｜MVP部署方案与执行清单
A3: 推荐最少改造方案：Vercel部署现有Web；Railway/Render运行现有NestJS API；Supabase提供PostgreSQL与Auth；Creem负责支付；LLM按调用付费。若坚持不使用Railway，需要先将NestJS和AI长任务改造成Vercel Functions/Workflow。价格以官方页面为准，表内于2026-07-13核对。
A5: 一、推荐架构与服务分工
A6: 层级 | B6: 推荐服务 | C6: 负责内容 | D6: 当前建议 | E6: 成本判断 | F6: 备注 | G6: 官方来源
A7: Web前端 | B7: Vercel | C7: 部署现有 apps/web、CDN、HTTPS、自定义域名 | D7: 当前已使用；继续保留 | E7: Hobby $0；Pro $20/月（商业上线按官方条款选择） | F7: 前端静态资源和普通Web请求 | G7: https://vercel.com/pricing
A8: 后端API | B8: Railway（推荐） | C8: 运行现有 NestJS apps/api、长请求、Health Check | D8: 推荐：最少改造现有后端 | E8: Free含少量资源；Hobby最低$5/月并含$5使用额度 | F8: 若改造成Vercel Functions/Workflow可不使用Railway | G8: https://railway.com/pricing
A9: 数据库 | B9: Supabase PostgreSQL | C9: StoryRun、StoryEvent、AiTask、用户与支付权益 | D9: 推荐 | E9: Free可用于开发；Pro $25/月起 | F9: 运行态权威数据 | G9: https://supabase.com/pricing
A10: 登录 | B10: Supabase Auth | C10: 邮箱验证码/Magic Link、会话和用户ID | D10: 推荐 | E10: Free额度足够早期MVP | F10: 前端anon key；服务端service role | G10: https://supabase.com/docs/guides/auth
A11: 文件 | B11: Vercel public / Supabase Storage | C11: 静态品牌资源放Vercel；用户生成资源放Storage | D11: 按需 | E11: 早期通常免费额度够用 | F11: MVP文本为主，暂不大量存视频 | G11: https://supabase.com/docs/guides/storage
A12: AI | B12: OpenAI/DeepSeek等 | C12: ActionGuard、角色反应、剧情表达 | D12: 必需 | E12: 按调用付费 | F12: 规则引擎仍是状态权威 | G12: https://platform.openai.com/docs / 具体模型供应商官方文档
A13: 支付 | B13: Creem | C13: Checkout、税务/MoR、Webhook、退款/争议 | D13: 正式收费必需 | E13: 通常按交易收费 | F13: 先Test Mode，审核通过后Live | G13: https://docs.creem.io/getting-started/quickstart
A14: 域名与邮件 | B14: Cloudflare DNS + Email Routing | C14: 域名解析、HTTPS辅助、support@转发 | D14: 推荐 | E14: 基础功能可免费 | F14: 客服邮箱需真实可收件 | G14: https://developers.cloudflare.com/email-routing/
A15: 监控 | B15: Vercel/Railway Logs + Sentry | C15: 错误、版本、AI失败与告警 | D15: 推荐 | E15: 早期可用免费额度 | F15: 禁止记录密钥和完整私密输入 | G15: https://sentry.io/pricing/
A16: 分析 | B16: 轻量分析工具 | C16: 来源、登录、开局、决策、结局、支付点击 | D16: 建议 | E16: 可先免费 | F16: 不上传完整自定义文本 | G16: 按实际采用的分析工具官方定价页
A18: 二、环境分层
A19: 环境 | B19: 用途 | C19: 数据库 | D19: AI | E19: 支付 | F19: 密钥 | G19: 数据策略
A20: local | B20: 本地开发 | C20: 本地/开发Supabase项目 | D20: mock/rules优先 | E20: Creem Test | F20: 开发密钥 | G20: 可随时重置
A21: test | B21: 自动化测试 | C21: 每次隔离或事务回滚 | D21: 固定mock | E21: 不调用真实支付 | F21: 测试密钥 | G21: CI自动执行
A22: staging | B22: 上线前试玩验收 | C22: 独立Supabase项目/Schema | D22: 真实模型+fallback+较低预算 | E22: Creem Test | F22: 独立密钥 | G22: 至少完成20局连续模拟
A23: production | B23: 正式Limited Beta | C23: 生产Supabase+备份 | D23: 真实模型+限额+告警 | E23: Creem Live或候补 | F23: 生产密钥 | G23: 与staging完全隔离
A25: 三、部署执行任务
A26: 编号 | B26: 模块 | C26: 部署任务 | D26: 完成标准 | E26: 服务/平台 | F26: 优先级 | G26: 上线阻断 | H26: 状态 | I26: 负责人 | J26: 前置依赖 | K26: 计划阶段 | L26: 卡点/下一步
A27: DEP-001 | B27: 架构决策 | C27: 确认MVP部署组合 | D27: 推荐 Vercel Web + Railway NestJS API + Supabase Auth/Postgres + LLM + Creem。 | E27: 全局 | F27: P0 | G27: 是 | H27: 进行中 | I27: 我 | J27: 代码审计 | K27: 第1天 | L27: 确认是否保留现有NestJS部署到Railway
A28: DEP-002 | B28: Supabase | C28: 创建开发项目 | D28: 创建项目、区域、数据库密码、anon/service role密钥并保存。 | E28: Supabase | F28: P0 | G28: 是 | H28: 未开始 | I28: 我 | K28: 第1天
A29: DEP-003 | B29: Supabase | C29: 创建staging/production隔离 | D29: 至少staging与production不共享数据库和密钥。 | E29: Supabase | F29: P0 | G29: 是 | H29: 未开始 | I29: 我 | J29: 开发项目 | K29: 第5天
A30: DEP-004 | B30: Supabase | C30: 执行Prisma迁移 | D30: 创建StoryRun/StoryEvent/AiTask/profiles/payment_events/entitlements。 | E30: Supabase | F30: P0 | G30: 是 | H30: 未开始 | I30: Codex | J30: 数据库模型 | K30: 第5天
A31: DEP-005 | B31: Supabase | C31: 配置RLS与服务端访问 | D31: 用户只能访问自己的run；service role仅API环境。 | E31: Supabase | F31: P0 | G31: 是 | H31: 未开始 | I31: Codex | J31: 登录/表结构 | K31: 第5天
A32: DEP-006 | B32: Supabase | C32: 启用备份与恢复记录 | D32: 生产阶段每日备份，记录恢复步骤和责任人。 | E32: Supabase | F32: P1 | G32: 是 | H32: 未开始 | I32: 我+Codex | J32: production | K32: 第6天
A33: DEP-007 | B33: Vercel | C33: 绑定正式域名 | D33: ourmanyworlds.com HTTPS稳定，www重定向策略明确。 | E33: Vercel/Cloudflare | F33: P0 | G33: 是 | H33: 已完成 | I33: 我 | K33: 第1天
A34: DEP-008 | B34: Vercel | C34: 配置构建命令与输出目录 | D34: apps/web生产构建可重复执行。 | E34: Vercel | F34: P0 | G34: 是 | H34: 待确认 | I34: Codex | J34: 代码审计 | K34: 第5天
A35: DEP-009 | B35: Vercel | C35: 配置前端环境变量 | D35: PUBLIC_API_BASE_URL、Supabase public URL/anon key、分析配置。 | E35: Vercel | F35: P0 | G35: 是 | H35: 未开始 | I35: 我+Codex | J35: API域名/Supabase | K35: 第6天
A36: DEP-010 | B36: Vercel | C36: 配置Preview与Production | D36: PR/分支预览不连接生产数据库和Live支付。 | E36: Vercel | F36: P0 | G36: 是 | H36: 未开始 | I36: Codex | J36: 环境分层 | K36: 第6天
A37: DEP-011 | B37: 后端平台 | C37: 创建Railway API服务 | D37: 从仓库部署apps/api，配置启动命令、端口和自动重启。 | E37: Railway | F37: P0 | G37: 是 | H37: 未开始 | I37: 我+Codex | J37: 架构决策 | K37: 第5天
A38: DEP-012 | B38: 后端平台 | C38: 配置Health Check | D38: /health返回200并检查数据库连接。 | E38: Railway | F38: P0 | G38: 是 | H38: 未开始 | I38: Codex | J38: API实现 | K38: 第5天
A39: DEP-013 | B39: 后端平台 | C39: 配置API域名 | D39: 使用api.ourmanyworlds.com或Vercel反向代理，启用HTTPS。 | E39: Railway/Cloudflare | F39: P0 | G39: 是 | H39: 未开始 | I39: 我 | J39: Railway服务 | K39: 第6天
A40: DEP-014 | B40: 后端平台 | C40: 配置资源与超时 | D40: 低配CPU/内存起步；AI请求25秒超时+1次重试+fallback。 | E40: Railway/API | F40: P0 | G40: 是 | H40: 未开始 | I40: Codex | J40: AI实现 | K40: 第6天
A41: DEP-015 | B41: 后端平台 | C41: 部署staging API | D41: 使用staging数据库、Creem Test、测试AI预算。 | E41: Railway | F41: P0 | G41: 是 | H41: 未开始 | I41: Codex | J41: staging环境 | K41: 第6天
A42: DEP-016 | B42: 后端平台 | C42: 部署production API | D42: 使用生产数据库、Live/候补支付和正式告警。 | E42: Railway | F42: P0 | G42: 是 | H42: 未开始 | I42: Codex | J42: staging验收 | K42: 第7天
A43: DEP-017 | B43: 域名/CORS | C43: 配置Web到API跨域 | D43: 只允许正式/预览域名；Cookie/Auth头正常。 | E43: API/Cloudflare | F43: P0 | G43: 是 | H43: 未开始 | I43: Codex | J43: API域名 | K43: 第6天
A44: DEP-018 | B44: Creem | C44: 配置Test API Key | D44: 后端能创建测试Checkout，密钥不进入前端。 | E44: Creem/API | F44: P0 | G44: 是 | H44: 进行中 | I44: 我+Codex | K44: 第4天
A45: DEP-019 | B45: Creem | C45: 配置Webhook公网地址 | D45: 完整URL /api/v4/webhooks/creem，订阅checkout/refund/dispute。 | E45: Creem/API | F45: P0 | G45: 是 | H45: 进行中 | I45: 我+Codex | J45: API公网域名 | K45: 第5天
A46: DEP-020 | B46: Creem | C46: 配置Webhook Secret | D46: 服务端校验签名和原始请求体。 | E46: Creem/API | F46: P0 | G46: 是 | H46: 未开始 | I46: 我+Codex | J46: Webhook地址 | K46: 第5天
A47: DEP-021 | B47: Creem | C47: Live环境切换 | D47: 审核通过后新建Live产品并替换Live环境变量。 | E47: Creem | F47: P0 | G47: 是 | H47: 未开始 | I47: 我 | J47: Creem审核/staging测试 | K47: 第7天
A48: DEP-022 | B48: AI | C48: 配置Provider密钥与模型 | D48: AI_API_KEY/BASE_URL/MODEL只在API环境。 | E48: Railway/API | F48: P0 | G48: 是 | H48: 未开始 | I48: 我+Codex | J48: AI provider | K48: 第5天
A49: DEP-023 | B49: AI | C49: 配置单局预算 | D49: 超时、重试、token、调用数和成本上限生效。 | E49: API | F49: P0 | G49: 是 | H49: 未开始 | I49: Codex | J49: AI实现 | K49: 第5天
A50: DEP-024 | B50: 日志监控 | C50: 接入结构化日志 | D50: requestId/runId/eventId/version/fallback/token/成本可查。 | E50: API/平台日志 | F50: P0 | G50: 是 | H50: 未开始 | I50: Codex | J50: API实现 | K50: 第5天
A51: DEP-025 | B51: 日志监控 | C51: 接入Sentry/告警 | D51: 5xx、存储失败、finalize失败、私密字段泄露和成本超限告警。 | E51: Sentry/Webhook | F51: P1 | G51: 否 | H51: 未开始 | I51: 我+Codex | J51: 日志 | K51: 第6天
A52: DEP-026 | B52: 安全 | C52: 配置密钥管理 | D52: 所有secret仅平台环境变量；执行仓库密钥扫描。 | E52: Vercel/Railway | F52: P0 | G52: 是 | H52: 未开始 | I52: 我+Codex | K52: 第6天
A53: DEP-027 | B53: 安全 | C53: 配置安全响应头 | D53: CSP、HSTS、X-Content-Type-Options、Referrer-Policy。 | E53: Vercel/API | F53: P1 | G53: 否 | H53: 未开始 | I53: Codex | J53: 生产域名 | K53: 第6天
A54: DEP-028 | B54: 数据 | C54: 配置备份和恢复演练 | D54: 备份后恢复到隔离环境，并从事件流校验快照。 | E54: Supabase | F54: P0 | G54: 是 | H54: 未开始 | I54: 我+Codex | J54: staging数据 | K54: 第6天
A55: DEP-029 | B55: 发布 | C55: 执行staging冒烟 | D55: 首页→登录→创建/进入房间→决策→谋划→刷新→结局/支付Test。 | E55: 全部 | F55: P0 | G55: 是 | H55: 未开始 | I55: Codex+我 | J55: P0开发完成 | K55: 第6天
A56: DEP-030 | B56: 发布 | C56: 执行20局模拟 | D56: A/B/C/Mixed、0/1/2谋划、AI失败、恢复、并发全部通过。 | E56: staging | F56: P0 | G56: 是 | H56: 未开始 | I56: Codex | J56: 测试脚本/staging | K56: 第6天
A57: DEP-031 | B57: 发布 | C57: 生产迁移与部署 | D57: 先数据库迁移，再API，再Web；记录版本号与时间。 | E57: 全部 | F57: P0 | G57: 是 | H57: 未开始 | I57: Codex+我 | J57: 发布闸门 | K57: 第7天
A58: DEP-032 | B58: 发布 | C58: 上线后冒烟 | D58: 生产完成一次真实登录、创建局、决策和恢复；支付按Live/候补检查。 | E58: production | F58: P0 | G58: 是 | H58: 未开始 | I58: Codex+我 | J58: 生产部署 | K58: 第7天
A59: DEP-033 | B59: 发布 | C59: 回滚方案 | D59: 保留上一版本、数据库回滚/前向修复脚本和紧急关闭支付开关。 | E59: 全部 | F59: P0 | G59: 是 | H59: 未开始 | I59: Codex+我 | J59: 迁移验证 | K59: 第6天
A60: DEP-034 | B60: 发布 | C60: 上线监控与客服 | D60: 上线24小时监控5xx/AI/成本/支付；support邮箱可响应。 | E60: 全部 | F60: P0 | G60: 是 | H60: 未开始 | I60: 我 | J60: 生产部署 | K60: 第7天
A62: 四、关键环境变量清单（只记录变量名，不在Excel填写真实Secret）
A63: 类别 | B63: 变量名 | C63: 使用位置 | D63: 是否Secret | E63: 环境 | F63: 说明
A64: Web | B64: PUBLIC_API_BASE_URL | C64: Vercel | D64: 否 | E64: staging/prod | F64: API公开地址或同域/api
A65: Supabase | B65: SUPABASE_URL | C65: Web/API | D65: 否 | E65: 全部 | F65: 项目URL
A66: Supabase | B66: SUPABASE_ANON_KEY | C66: Web | D66: 否 | E66: 全部 | F66: 仅公开anon key
A67: Supabase | B67: SUPABASE_SERVICE_ROLE_KEY | C67: API | D67: 是 | E67: 全部 | F67: 绝不进入前端
A68: Database | B68: DATABASE_URL | C68: API/Prisma | D68: 是 | E68: 全部 | F68: PostgreSQL连接串
A69: AI | B69: AI_CAUSAL_PROVIDER | C69: API | D69: 否 | E69: 全部 | F69: rules/mock/openai/deepseek
A70: AI | B70: AI_BASE_URL | C70: API | D70: 否 | E70: staging/prod | F70: 模型服务地址
A71: AI | B71: AI_MODEL | C71: API | D71: 否 | E71: staging/prod | F71: 模型名称
A72: AI | B72: AI_API_KEY | C72: API | D72: 是 | E72: staging/prod | F72: 模型密钥
A73: AI | B73: AI_TIMEOUT_MS | C73: API | D73: 否 | E73: 全部 | F73: 建议25000
A74: AI | B74: AI_MAX_RETRIES | C74: API | D74: 否 | E74: 全部 | F74: 建议1
... A83: Backup | B83: BACKUP_RETENTION_DAYS | C83: API/运维 | D83: 否 | E83: production | F83: 建议30

Sheet 研发总览
A1: AI多人剧情推演｜研发、测试与部署总览
A3: 本页按新增细分任务自动汇总。注意：开发拆分后包含登录、数据库、后端、AI、支付、测试与部署，计算完成度可能明显低于原先“约30%”的体感。
A5: 开发任务 | D5: 测试用例 | G5: 模拟对局 | J5: 部署任务
A6: 总数 | B6: 已完成 | C6: 完成率 | D6: 总数 | E6: 已通过 | F6: 通过率 | G6: 总数 | H6: 已通过 | I6: 通过率 | J6: 总数 | K6: 已完成 | L6: 完成率
A7: =COUNTA(开发进度!$D$5:$D$300) -> 141 | B7: =COUNTIF(开发进度!$J$5:$J$300,"已完成") -> 86 | C7: =IFERROR(AVERAGE(开发进度!$K$5:$K$300),0) -> 0.75755396 | D7: =COUNTA(测试进度!$A$5:$A$400) -> 207 | E7: =COUNTIF(测试进度!$J$5:$J$400,"通过") -> 0 | F7: =IFERROR(E7/D7,0) -> 0 | G7: =COUNTA(模拟对局!$A$5:$A$100) -> 35 | H7: =COUNTIF(模拟对局!$H$5:$H$100,"通过") -> 0 | I7: =IFERROR(H7/G7,0) -> 0 | J7: =COUNTA(部署方案!$C$27:$C$60) -> 34 | K7: =COUNTIF(部署方案!$H$27:$H$60,"已完成") -> 1 | L7: =IFERROR(K7/J7,0) -> 0.029411765
A9: 开发模块进度 | H9: 测试模块进度
A10: 模块 | B10: 任务数 | C10: 已完成 | D10: 进行中/待审核 | E10: 已阻塞 | F10: 完成率 | H10: 模块 | I10: 用例数 | J10: 通过 | K10: 失败/阻塞 | L10: 通过率
A11: 工程基线 | B11: =COUNTIF(开发进度!$B$5:$B$300,A11) -> 8 | C11: =COUNTIFS(开发进度!$B$5:$B$300,A11,开发进度!$J$5:$J$300,"已完成") -> 5 | D11: =COUNTIFS(开发进度!$B$5:$B$300,A11,开发进度!$J$5:$J$300,"进行中")+COUNTIFS(开发进度!$B$5:$B$300,A11,开发进度!$J$5:$J$300,"待审核") -> 2 | E11: =COUNTIFS(开发进度!$B$5:$B$300,A11,开发进度!$J$5:$J$300,"已阻塞") -> 0 | F11: =IFERROR(AVERAGEIF(开发进度!$B$5:$B$300,A11,开发进度!$K$5:$K$300),0) -> 0.85714286 | H11: 功能测试 | I11: =COUNTIF(测试进度!$C$5:$C$400,H11) -> 25 | J11: =COUNTIFS(测试进度!$C$5:$C$400,H11,测试进度!$J$5:$J$400,"通过") -> 0 | K11: =COUNTIFS(测试进度!$C$5:$C$400,H11,测试进度!$J$5:$J$400,"失败")+COUNTIFS(测试进度!$C$5:$C$400,H11,测试进度!$J$5:$J$400,"已阻塞") -> 0 | L11: =IFERROR(J11/I11,0) -> 0
A12: 登录与账号 | B12: =COUNTIF(开发进度!$B$5:$B$300,A12) -> 10 | C12: =COUNTIFS(开发进度!$B$5:$B$300,A12,开发进度!$J$5:$J$300,"已完成") -> 4 | D12: =COUNTIFS(开发进度!$B$5:$B$300,A12,开发进度!$J$5:$J$300,"进行中")+COUNTIFS(开发进度!$B$5:$B$300,A12,开发进度!$J$5:$J$300,"待审核") -> 3 | E12: =COUNTIFS(开发进度!$B$5:$B$300,A12,开发进度!$J$5:$J$300,"已阻塞") -> 0 | F12: =IFERROR(AVERAGEIF(开发进度!$B$5:$B$300,A12,开发进度!$K$5:$K$300),0) -> 0.55 | H12: ActionGuard | I12: =COUNTIF(测试进度!$C$5:$C$400,H12) -> 18 | J12: =COUNTIFS(测试进度!$C$5:$C$400,H12,测试进度!$J$5:$J$400,"通过") -> 0 | K12: =COUNTIFS(测试进度!$C$5:$C$400,H12,测试进度!$J$5:$J$400,"失败")+COUNTIFS(测试进度!$C$5:$C$400,H12,测试进度!$J$5:$J$400,"已阻塞") -> 0 | L12: =IFERROR(J12/I12,0) -> 0
A13: 入口与房间 | B13: =COUNTIF(开发进度!$B$5:$B$300,A13) -> 9 | C13: =COUNTIFS(开发进度!$B$5:$B$300,A13,开发进度!$J$5:$J$300,"已完成") -> 7 | D13: =COUNTIFS(开发进度!$B$5:$B$300,A13,开发进度!$J$5:$J$300,"进行中")+COUNTIFS(开发进度!$B$5:$B$300,A13,开发进度!$J$5:$J$300,"待审核") -> 0 | E13: =COUNTIFS(开发进度!$B$5:$B$300,A13,开发进度!$J$5:$J$300,"已阻塞") -> 0 | F13: =IFERROR(AVERAGEIF(开发进度!$B$5:$B$300,A13,开发进度!$K$5:$K$300),0) -> 0.875 | H13: 因果与状态 | I13: =COUNTIF(测试进度!$C$5:$C$400,H13) -> 22 | J13: =COUNTIFS(测试进度!$C$5:$C$400,H13,测试进度!$J$5:$J$400,"通过") -> 0 | K13: =COUNTIFS(测试进度!$C$5:$C$400,H13,测试进度!$J$5:$J$400,"失败")+COUNTIFS(测试进度!$C$5:$C$400,H13,测试进度!$J$5:$J$400,"已阻塞") -> 0 | L13: =IFERROR(J13/I13,0) -> 0
A14: 数据库与运行态 | B14: =COUNTIF(开发进度!$B$5:$B$300,A14) -> 10 | C14: =COUNTIFS(开发进度!$B$5:$B$300,A14,开发进度!$J$5:$J$300,"已完成") -> 9 | D14: =COUNTIFS(开发进度!$B$5:$B$300,A14,开发进度!$J$5:$J$300,"进行中")+COUNTIFS(开发进度!$B$5:$B$300,A14,开发进度!$J$5:$J$300,"待审核") -> 1 | E14: =COUNTIFS(开发进度!$B$5:$B$300,A14,开发进度!$J$5:$J$300,"已阻塞") -> 0 | F14: =IFERROR(AVERAGEIF(开发进度!$B$5:$B$300,A14,开发进度!$K$5:$K$300),0) -> 0.95 | H14: 信息隔离 | I14: =COUNTIF(测试进度!$C$5:$C$400,H14) -> 10 | J14: =COUNTIFS(测试进度!$C$5:$C$400,H14,测试进度!$J$5:$J$400,"通过") -> 0 | K14: =COUNTIFS(测试进度!$C$5:$C$400,H14,测试进度!$J$5:$J$400,"失败")+COUNTIFS(测试进度!$C$5:$C$400,H14,测试进度!$J$5:$J$400,"已阻塞") -> 0 | L14: =IFERROR(J14/I14,0) -> 0
A15: 后端API | B15: =COUNTIF(开发进度!$B$5:$B$300,A15) -> 14 | C15: =COUNTIFS(开发进度!$B$5:$B$300,A15,开发进度!$J$5:$J$300,"已完成") -> 14 | D15: =COUNTIFS(开发进度!$B$5:$B$300,A15,开发进度!$J$5:$J$300,"进行中")+COUNTIFS(开发进度!$B$5:$B$300,A15,开发进度!$J$5:$J$300,"待审核") -> 0 | E15: =COUNTIFS(开发进度!$B$5:$B$300,A15,开发进度!$J$5:$J$300,"已阻塞") -> 0 | F15: =IFERROR(AVERAGEIF(开发进度!$B$5:$B$300,A15,开发进度!$K$5:$K$300),0) -> 1 | H15: 分支差异 | I15: =COUNTIF(测试进度!$C$5:$C$400,H15) -> 6 | J15: =COUNTIFS(测试进度!$C$5:$C$400,H15,测试进度!$J$5:$J$400,"通过") -> 0 | K15: =COUNTIFS(测试进度!$C$5:$C$400,H15,测试进度!$J$5:$J$400,"失败")+COUNTIFS(测试进度!$C$5:$C$400,H15,测试进度!$J$5:$J$400,"已阻塞") -> 0 | L15: =IFERROR(J15/I15,0) -> 0
A16: 主游戏UI | B16: =COUNTIF(开发进度!$B$5:$B$300,A16) -> 17 | C16: =COUNTIFS(开发进度!$B$5:$B$300,A16,开发进度!$J$5:$J$300,"已完成") -> 1 | D16: =COUNTIFS(开发进度!$B$5:$B$300,A16,开发进度!$J$5:$J$300,"进行中")+COUNTIFS(开发进度!$B$5:$B$300,A16,开发进度!$J$5:$J$300,"待审核") -> 16 | E16: =COUNTIFS(开发进度!$B$5:$B$300,A16,开发进度!$J$5:$J$300,"已阻塞") -> 0 | F16: =IFERROR(AVERAGEIF(开发进度!$B$5:$B$300,A16,开发进度!$K$5:$K$300),0) -> 0.88235294 | H16: 主动谋划路径 | I16: =COUNTIF(测试进度!$C$5:$C$400,H16) -> 10 | J16: =COUNTIFS(测试进度!$C$5:$C$400,H16,测试进度!$J$5:$J$400,"通过") -> 0 | K16: =COUNTIFS(测试进度!$C$5:$C$400,H16,测试进度!$J$5:$J$400,"失败")+COUNTIFS(测试进度!$C$5:$C$400,H16,测试进度!$J$5:$J$400,"已阻塞") -> 0 | L16: =IFERROR(J16/I16,0) -> 0
A17: 主线决策 | B17: =COUNTIF(开发进度!$B$5:$B$300,A17) -> 12 | C17: =COUNTIFS(开发进度!$B$5:$B$300,A17,开发进度!$J$5:$J$300,"已完成") -> 12 | D17: =COUNTIFS(开发进度!$B$5:$B$300,A17,开发进度!$J$5:$J$300,"进行中")+COUNTIFS(开发进度!$B$5:$B$300,A17,开发进度!$J$5:$J$300,"待审核") -> 0 | E17: =COUNTIFS(开发进度!$B$5:$B$300,A17,开发进度!$J$5:$J$300,"已阻塞") -> 0 | F17: =IFERROR(AVERAGEIF(开发进度!$B$5:$B$300,A17,开发进度!$K$5:$K$300),0) -> 1 | H17: API并发与幂等 | I17: =COUNTIF(测试进度!$C$5:$C$400,H17) -> 22 | J17: =COUNTIFS(测试进度!$C$5:$C$400,H17,测试进度!$J$5:$J$400,"通过") -> 0 | K17: =COUNTIFS(测试进度!$C$5:$C$400,H17,测试进度!$J$5:$J$400,"失败")+COUNTIFS(测试进度!$C$5:$C$400,H17,测试进度!$J$5:$J$400,"已阻塞") -> 0 | L17: =IFERROR(J17/I17,0) -> 0
A18: 主动谋划与关键事件 | B18: =COUNTIF(开发进度!$B$5:$B$300,A18) -> 13 | C18: =COUNTIFS(开发进度!$B$5:$B$300,A18,开发进度!$J$5:$J$300,"已完成") -> 13 | D18: =COUNTIFS(开发进度!$B$5:$B$300,A18,开发进度!$J$5:$J$300,"进行中")+COUNTIFS(开发进度!$B$5:$B$300,A18,开发进度!$J$5:$J$300,"待审核") -> 0 | E18: =COUNTIFS(开发进度!$B$5:$B$300,A18,开发进度!$J$5:$J$300,"已阻塞") -> 0 | F18: =IFERROR(AVERAGEIF(开发进度!$B$5:$B$300,A18,开发进度!$K$5:$K$300),0) -> 1 | H18: AI失败与恢复 | I18: =COUNTIF(测试进度!$C$5:$C$400,H18) -> 13 | J18: =COUNTIFS(测试进度!$C$5:$C$400,H18,测试进度!$J$5:$J$400,"通过") -> 0 | K18: =COUNTIFS(测试进度!$C$5:$C$400,H18,测试进度!$J$5:$J$400,"失败")+COUNTIFS(测试进度!$C$5:$C$400,H18,测试进度!$J$5:$J$400,"已阻塞") -> 0 | L18: =IFERROR(J18/I18,0) -> 0
A19: 天数与结局 | B19: =COUNTIF(开发进度!$B$5:$B$300,A19) -> 8 | C19: =COUNTIFS(开发进度!$B$5:$B$300,A19,开发进度!$J$5:$J$300,"已完成") -> 8 | D19: =COUNTIFS(开发进度!$B$5:$B$300,A19,开发进度!$J$5:$J$300,"进行中")+COUNTIFS(开发进度!$B$5:$B$300,A19,开发进度!$J$5:$J$300,"待审核") -> 0 | E19: =COUNTIFS(开发进度!$B$5:$B$300,A19,开发进度!$J$5:$J$300,"已阻塞") -> 0 | F19: =IFERROR(AVERAGEIF(开发进度!$B$5:$B$300,A19,开发进度!$K$5:$K$300),0) -> 1 | H19: Web/UI | I19: =COUNTIF(测试进度!$C$5:$C$400,H19) -> 33 | J19: =COUNTIFS(测试进度!$C$5:$C$400,H19,测试进度!$J$5:$J$400,"通过") -> 0 | K19: =COUNTIFS(测试进度!$C$5:$C$400,H19,测试进度!$J$5:$J$400,"失败")+COUNTIFS(测试进度!$C$5:$C$400,H19,测试进度!$J$5:$J$400,"已阻塞") -> 0 | L19: =IFERROR(J19/I19,0) -> 0
A20: AI推演 | B20: =COUNTIF(开发进度!$B$5:$B$300,A20) -> 12 | C20: =COUNTIFS(开发进度!$B$5:$B$300,A20,开发进度!$J$5:$J$300,"已完成") -> 12 | D20: =COUNTIFS(开发进度!$B$5:$B$300,A20,开发进度!$J$5:$J$300,"进行中")+COUNTIFS(开发进度!$B$5:$B$300,A20,开发进度!$J$5:$J$300,"待审核") -> 0 | E20: =COUNTIFS(开发进度!$B$5:$B$300,A20,开发进度!$J$5:$J$300,"已阻塞") -> 0 | F20: =IFERROR(AVERAGEIF(开发进度!$B$5:$B$300,A20,开发进度!$K$5:$K$300),0) -> 1 | H20: 登录与账号 | I20: =COUNTIF(测试进度!$C$5:$C$400,H20) -> 10 | J20: =COUNTIFS(测试进度!$C$5:$C$400,H20,测试进度!$J$5:$J$400,"通过") -> 0 | K20: =COUNTIFS(测试进度!$C$5:$C$400,H20,测试进度!$J$5:$J$400,"失败")+COUNTIFS(测试进度!$C$5:$C$400,H20,测试进度!$J$5:$J$400,"已阻塞") -> 0 | L20: =IFERROR(J20/I20,0) -> 0
A21: 支付与权益 | B21: =COUNTIF(开发进度!$B$5:$B$300,A21) -> 8 | C21: =COUNTIFS(开发进度!$B$5:$B$300,A21,开发进度!$J$5:$J$300,"已完成") -> 1 | D21: =COUNTIFS(开发进度!$B$5:$B$300,A21,开发进度!$J$5:$J$300,"进行中")+COUNTIFS(开发进度!$B$5:$B$300,A21,开发进度!$J$5:$J$300,"待审核") -> 3 | E21: =COUNTIFS(开发进度!$B$5:$B$300,A21,开发进度!$J$5:$J$300,"已阻塞") -> 0 | F21: =IFERROR(AVERAGEIF(开发进度!$B$5:$B$300,A21,开发进度!$K$5:$K$300),0) -> 0.4125 | H21: 入口与房间 | I21: =COUNTIF(测试进度!$C$5:$C$400,H21) -> 8 | J21: =COUNTIFS(测试进度!$C$5:$C$400,H21,测试进度!$J$5:$J$400,"通过") -> 0 | K21: =COUNTIFS(测试进度!$C$5:$C$400,H21,测试进度!$J$5:$J$400,"失败")+COUNTIFS(测试进度!$C$5:$C$400,H21,测试进度!$J$5:$J$400,"已阻塞") -> 0 | L21: =IFERROR(J21/I21,0) -> 0
A22: 安全与可观测性 | B22: =COUNTIF(开发进度!$B$5:$B$300,A22) -> 10 | C22: =COUNTIFS(开发进度!$B$5:$B$300,A22,开发进度!$J$5:$J$300,"已完成") -> 0 | D22: =COUNTIFS(开发进度!$B$5:$B$300,A22,开发进度!$J$5:$J$300,"进行中")+COUNTIFS(开发进度!$B$5:$B$300,A22,开发进度!$J$5:$J$300,"待审核") -> 0 | E22: =COUNTIFS(开发进度!$B$5:$B$300,A22,开发进度!$J$5:$J$300,"已阻塞") -> 0 | F22: =IFERROR(AVERAGEIF(开发进度!$B$5:$B$300,A22,开发进度!$K$5:$K$300),0) -> 0 | H22: 剧本配置 | I22: =COUNTIF(测试进度!$C$5:$C$400,H22) -> 8 | J22: =COUNTIFS(测试进度!$C$5:$C$400,H22,测试进度!$J$5:$J$400,"通过") -> 0 | K22: =COUNTIFS(测试进度!$C$5:$C$400,H22,测试进度!$J$5:$J$400,"失败")+COUNTIFS(测试进度!$C$5:$C$400,H22,测试进度!$J$5:$J$400,"已阻塞") -> 0 | L22: =IFERROR(J22/I22,0) -> 0
A23: 部署与发布 | B23: =COUNTIF(开发进度!$B$5:$B$300,A23) -> 10 | C23: =COUNTIFS(开发进度!$B$5:$B$300,A23,开发进度!$J$5:$J$300,"已完成") -> 0 | D23: =COUNTIFS(开发进度!$B$5:$B$300,A23,开发进度!$J$5:$J$300,"进行中")+COUNTIFS(开发进度!$B$5:$B$300,A23,开发进度!$J$5:$J$300,"待审核") -> 0 | E23: =COUNTIFS(开发进度!$B$5:$B$300,A23,开发进度!$J$5:$J$300,"已阻塞") -> 0 | F23: =IFERROR(AVERAGEIF(开发进度!$B$5:$B$300,A23,开发进度!$K$5:$K$300),0) -> 0 | H23: 支付与权益 | I23: =COUNTIF(测试进度!$C$5:$C$400,H23) -> 10 | J23: =COUNTIFS(测试进度!$C$5:$C$400,H23,测试进度!$J$5:$J$400,"通过") -> 0 | K23: =COUNTIFS(测试进度!$C$5:$C$400,H23,测试进度!$J$5:$J$400,"失败")+COUNTIFS(测试进度!$C$5:$C$400,H23,测试进度!$J$5:$J$400,"已阻塞") -> 0 | L23: =IFERROR(J23/I23,0) -> 0
H24: 部署与运维 | I24: =COUNTIF(测试进度!$C$5:$C$400,H24) -> 12 | J24: =COUNTIFS(测试进度!$C$5:$C$400,H24,测试进度!$J$5:$J$400,"通过") -> 0 | K24: =COUNTIFS(测试进度!$C$5:$C$400,H24,测试进度!$J$5:$J$400,"失败")+COUNTIFS(测试进度!$C$5:$C$400,H24,测试进度!$J$5:$J$400,"已阻塞") -> 0 | L24: =IFERROR(J24/I24,0) -> 0
A26: 发布闸门（全部满足后再公开Limited Beta）
A27: 闸门 | B27: 判定标准 | C27: 当前状态 | D27: 责任人 | E27: 证据/链接 | H27: 闸门 | I27: 判定标准 | J27: 当前状态 | K27: 责任人 | L27: 证据/链接
A28: P0开发完成 | B28: 开发进度中P0且上线阻断=是的任务全部已完成 | C28: =IF(COUNTIFS(开发进度!$H$5:$H$300,"P0",开发进度!$I$5:$I$300,"是",开发进度!$J$5:$J$300,"<>已完成")=0,"通过","未通过") -> 未通过 | D28: Codex+我 | H28: 登录与房间 | I28: AUTH-001、ROOM-001、ROOM-003通过 | J28: =IF(AND(INDEX(测试进度!$J$5:$J$400,MATCH("AUTH-001",测试进度!$A$5:$A$400,0))="通过",INDEX(测试进度!$J$5:$J$400,MATCH("ROOM-001",测试进度!$A$5:$A$400,0))="通过",INDEX(测试进度!$J$5:$J$400,MATCH("ROOM-003",测试进度!$A$5:$A$400,0))="通过"),"通过","未通过") -> 未通过 | K28: Codex
A29: P0测试通过 | B29: 测试进度中P0上线阻断用例全部通过 | C29: =IF(COUNTIFS(测试进度!$H$5:$H$400,"P0",测试进度!$I$5:$I$400,"是",测试进度!$J$5:$J$400,"<>通过")=0,"通过","未通过") -> 未通过 | D29: Codex | H29: AI与恢复 | I29: R-002、R-008、R-009通过 | J29: =IF(AND(INDEX(测试进度!$J$5:$J$400,MATCH("R-002",测试进度!$A$5:$A$400,0))="通过",INDEX(测试进度!$J$5:$J$400,MATCH("R-008",测试进度!$A$5:$A$400,0))="通过",INDEX(测试进度!$J$5:$J$400,MATCH("R-009",测试进度!$A$5:$A$400,0))="通过"),"通过","未通过") -> 未通过 | K29: Codex
A30: 核心7天闭环 | B30: F-007、F-010及最终裁决相关测试通过 | C30: =IF(AND(INDEX(测试进度!$J$5:$J$400,MATCH("F-007",测试进度!$A$5:$A$400,0))="通过",INDEX(测试进度!$J$5:$J$400,MATCH("F-010",测试进度!$A$5:$A$400,0))="通过"),"通过","未通过") -> 未通过 | D30: Codex | H30: Staging冒烟 | I30: DEP-009通过且部署任务“执行staging冒烟”已完成 | J30: =IF(INDEX(测试进度!$J$5:$J$400,MATCH("DEP-009",测试进度!$A$5:$A$400,0))="通过","通过","未通过") -> 未通过 | K30: Codex+我
A31: 20局模拟 | B31: SIM-025通过且无P0缺陷 | C31: =IF(INDEX(模拟对局!$H$5:$H$100,MATCH("SIM-025",模拟对局!$A$5:$A$100,0))="通过","通过","未通过") -> 未通过 | D31: Codex+我 | H31: 支付或候补 | I31: PAY-002通过；若Live未通过则候补入口已测试 | J31: =IF(INDEX(测试进度!$J$5:$J$400,MATCH("PAY-002",测试进度!$A$5:$A$400,0))="通过","通过","未通过") -> 未通过 | K31: 我+Codex
